[["案名:劃定臺北市大安區瑞安段一小段221-3地號等3筆土地為更\n新單元檢討書\n申請人:趙玉琴\n一、計畫位置:本更新單元位於臺北市大安區建國南路二段69巷,\n信義路三段134巷及建國南路二段所圍街廓內之東\n二、計畫範圍:臺北市大安區瑞安段一小段221-3 , 225、226地號\n等3筆土地。\n三、計畫面積: 1,228平方公尺。\n四、法令依據:都市更新條例第11條及臺北市都市更新自治條例第\n15條。\n厅\n企\n","案","名",":","劃定","臺北市","大安","區","瑞安","段","一小段","221-3","地","號","等","3","筆","土地","為","更","新","單元","檢討書","申請人",":","趙玉琴","一","、","計畫","位置",":","本","更新","單元","位於","臺北市","大安","區","建國","南路","二段","69","巷",",","信義","路三段","134","巷","及","建國","南路","二段","所","圍","街廓","內","之","東","二","、","計畫","範圍",":","臺北市","大安","區","瑞安","段","一小段","221-3",",","225、226","地","號","等","3","筆","土地","。","三","、","計畫","面積",":","1,228","平方公尺","。","四","、","法令","依據",":","都市","更新","條例","第","11","條","及","臺北市","都市","更新","自治","條例","第","15","條","。","厅","企"],{"responses":[{"faceAnnotations":[],"landmarkAnnotations":[],"logoAnnotations":[],"labelAnnotations":[],"textAnnotations":[{"mid":"","locale":"zh-Hant","description":"案名:劃定臺北市大安區瑞安段一小段221-3地號等3筆土地為更\n新單元檢討書\n申請人:趙玉琴\n一、計畫位置:本更新單元位於臺北市大安區建國南路二段69巷,\n信義路三段134巷及建國南路二段所圍街廓內之東\n二、計畫範圍:臺北市大安區瑞安段一小段221-3 , 225、226地號\n等3筆土地。\n三、計畫面積: 1,228平方公尺。\n四、法令依據:都市更新條例第11條及臺北市都市更新自治條例第\n15條。\n厅\n企\n","score":0,"confidence":0,"topicality":0,"boundingPoly":{"vertices":[{"x":390,"y":373},{"x":2135,"y":373},{"x":2135,"y":3212},{"x":390,"y":3212}]},"locations":[],"properties":[]},{"mid":"","locale":"","description":"案","score":0,"confidence":0,"topicality":0,"boundingPoly":{"vertices":[{"x":449,"y":375},{"x":493,"y":375},{"x":493,"y":428},{"x":449,"y":428}]},"locations":[],"properties":[]},{"mid":"","locale":"","description":"名","score":0,"confidence":0,"topicality":0,"boundingPoly":{"vertices":[{"x":500,"y":377},{"x":547,"y":377},{"x":547,"y":426},{"x":500,"y":426}]},"locations":[],"properties":[]},{"mid":"","locale":"","description":":","score":0,"confidence":0,"topicality":0,"boundingPoly":{"vertices":[{"x":574,"y":380},{"x":587,"y":380},{"x":587,"y":414},{"x":574,"y":414}]},"locations":[],"properties":[]},{"mid":"","locale":"","description":"劃定","score":0,"confidence":0,"topicality":0,"boundingPoly":{"vertices":[{"x":610,"y":375},{"x":719,"y":375},{"x":719,"y":429},{"x":610,"y":429}]},"locations":[],"properties":[]},{"mid":"","locale":"","description":"臺北市","score":0,"confidence":0,"topicality":0,"boundingPoly":{"vertices":[{"x":728,"y":373},{"x":895,"y":373},{"x":895,"y":429},{"x":728,"y":429}]},"locations":[],"properties":[]},{"mid":"","locale":"","description":"大安","score":0,"confidence":0,"topicality":0,"boundingPoly":{"vertices":[{"x":901,"y":378},{"x":1015,"y":378},{"x":1015,"y":427},{"x":901,"y":427}]},"locations":[],"properties":[]},{"mid":"","locale":"","description":"區","score":0,"confidence":0,"topicality":0,"boundingPoly":{"vertices":[{"x":1023,"y":377},{"x":1070,"y":377},{"x":1070,"y":426},{"x":1023,"y":426}]},"locations":[],"properties":[]},{"mid":"","locale":"","description":"瑞安","score":0,"confidence":0,"topicality":0,"boundingPoly":{"vertices":[{"x":1079,"y":378},{"x":1192,"y":378},{"x":1192,"y":429},{"x":1079,"y":429}]},"locations":[],"properties":[]},{"mid":"","locale":"","description":"段","score":0,"confidence":0,"topicality":0,"boundingPoly":{"vertices":[{"x":1196,"y":377},{"x":1255,"y":377},{"x":1255,"y":426},{"x":1196,"y":426}]},"locations":[],"properties":[]},{"mid":"","locale":"","description":"一小段","score":0,"confidence":0,"topicality":0,"boundingPoly":{"vertices":[{"x":1259,"y":377},{"x":1430,"y":377},{"x":1430,"y":428},{"x":1259,"y":428}]},"locations":[],"properties":[]},{"mid":"","locale":"","description":"221-3","score":0,"confidence":0,"topicality":0,"boundingPoly":{"vertices":[{"x":1446,"y":378},{"x":1579,"y":378},{"x":1579,"y":420},{"x":1446,"y":420}]},"locations":[],"properties":[]},{"mid":"","locale":"","description":"地","score":0,"confidence":0,"topicality":0,"boundingPoly":{"vertices":[{"x":1597,"y":375},{"x":1655,"y":375},{"x":1655,"y":424},{"x":1597,"y":424}]},"locations":[],"properties":[]},{"mid":"","locale":"","description":"號","score":0,"confidence":0,"topicality":0,"boundingPoly":{"vertices":[{"x":1659,"y":377},{"x":1713,"y":377},{"x":1713,"y":426},{"x":1659,"y":426}]},"locations":[],"properties":[]},{"mid":"","locale":"","description":"等","score":0,"confidence":0,"topicality":0,"boundingPoly":{"vertices":[{"x":1720,"y":373},{"x":1766,"y":373},{"x":1766,"y":429},{"x":1720,"y":429}]},"locations":[],"properties":[]},{"mid":"","locale":"","description":"3","score":0,"confidence":0,"topicality":0,"boundingPoly":{"vertices":[{"x":1785,"y":378},{"x":1812,"y":378},{"x":1812,"y":420},{"x":1785,"y":420}]},"locations":[],"properties":[]},{"mid":"","locale":"","description":"筆","score":0,"confidence":0,"topicality":0,"boundingPoly":{"vertices":[{"x":1838,"y":373},{"x":1885,"y":373},{"x":1885,"y":420},{"x":1838,"y":420}]},"locations":[],"properties":[]},{"mid":"","locale":"","description":"土地","score":0,"confidence":0,"topicality":0,"boundingPoly":{"vertices":[{"x":1893,"y":377},{"x":2006,"y":377},{"x":2006,"y":424},{"x":1893,"y":424}]},"locations":[],"properties":[]},{"mid":"","locale":"","description":"為","score":0,"confidence":0,"topicality":0,"boundingPoly":{"vertices":[{"x":2013,"y":375},{"x":2060,"y":375},{"x":2060,"y":429},{"x":2013,"y":429}]},"locations":[],"properties":[]},{"mid":"","locale":"","description":"更","score":0,"confidence":0,"topicality":0,"boundingPoly":{"vertices":[{"x":2072,"y":377},{"x":2123,"y":377},{"x":2123,"y":430},{"x":2072,"y":430}]},"locations":[],"properties":[]},{"mid":"","locale":"","description":"新","score":0,"confidence":0,"topicality":0,"boundingPoly":{"vertices":[{"x":582,"y":526},{"x":634,"y":526},{"x":634,"y":572},{"x":582,"y":572}]},"locations":[],"properties":[]},{"mid":"","locale":"","description":"單元","score":0,"confidence":0,"topicality":0,"boundingPoly":{"vertices":[{"x":642,"y":522},{"x":752,"y":523},{"x":752,"y":578},{"x":642,"y":577}]},"locations":[],"properties":[]},{"mid":"","locale":"","description":"檢討書","score":0,"confidence":0,"topicality":0,"boundingPoly":{"vertices":[{"x":759,"y":524},{"x":927,"y":525},{"x":927,"y":580},{"x":759,"y":579}]},"locations":[],"properties":[]},{"mid":"","locale":"","description":"申請人","score":0,"confidence":0,"topicality":0,"boundingPoly":{"vertices":[{"x":392,"y":731},{"x":558,"y":729},{"x":559,"y":784},{"x":393,"y":786}]},"locations":[],"properties":[]},{"mid":"","locale":"","description":":","score":0,"confidence":0,"topicality":0,"boundingPoly":{"vertices":[{"x":581,"y":738},{"x":593,"y":738},{"x":593,"y":771},{"x":581,"y":771}]},"locations":[],"properties":[]},{"mid":"","locale":"","description":"趙玉琴","score":0,"confidence":0,"topicality":0,"boundingPoly":{"vertices":[{"x":618,"y":735},{"x":791,"y":733},{"x":792,"y":785},{"x":619,"y":787}]},"locations":[],"properties":[]},{"mid":"","locale":"","description":"一","score":0,"confidence":0,"topicality":0,"boundingPoly":{"vertices":[{"x":390,"y":904},{"x":436,"y":904},{"x":436,"y":914},{"x":390,"y":914}]},"locations":[],"properties":[]},{"mid":"","locale":"","description":"、","score":0,"confidence":0,"topicality":0,"boundingPoly":{"vertices":[{"x":464,"y":903},{"x":479,"y":903},{"x":479,"y":918},{"x":464,"y":918}]},"locations":[],"properties":[]},{"mid":"","locale":"","description":"計畫","score":0,"confidence":0,"topicality":0,"boundingPoly":{"vertices":[{"x":503,"y":884},{"x":610,"y":884},{"x":610,"y":938},{"x":503,"y":938}]},"locations":[],"properties":[]},{"mid":"","locale":"","description":"位置","score":0,"confidence":0,"topicality":0,"boundingPoly":{"vertices":[{"x":622,"y":886},{"x":731,"y":886},{"x":731,"y":935},{"x":622,"y":935}]},"locations":[],"properties":[]},{"mid":"","locale":"","description":":","score":0,"confidence":0,"topicality":0,"boundingPoly":{"vertices":[{"x":757,"y":891},{"x":770,"y":891},{"x":770,"y":923},{"x":757,"y":923}]},"locations":[],"properties":[]},{"mid":"","locale":"","description":"本","score":0,"confidence":0,"topicality":0,"boundingPoly":{"vertices":[{"x":798,"y":886},{"x":854,"y":886},{"x":854,"y":937},{"x":798,"y":937}]},"locations":[],"properties":[]},{"mid":"","locale":"","description":"更新","score":0,"confidence":0,"topicality":0,"boundingPoly":{"vertices":[{"x":860,"y":886},{"x":967,"y":886},{"x":967,"y":937},{"x":860,"y":937}]},"locations":[],"properties":[]},{"mid":"","locale":"","description":"單元","score":0,"confidence":0,"topicality":0,"boundingPoly":{"vertices":[{"x":973,"y":884},{"x":1087,"y":884},{"x":1087,"y":933},{"x":973,"y":933}]},"locations":[],"properties":[]},{"mid":"","locale":"","description":"位於","score":0,"confidence":0,"topicality":0,"boundingPoly":{"vertices":[{"x":1093,"y":891},{"x":1207,"y":891},{"x":1207,"y":932},{"x":1093,"y":932}]},"locations":[],"properties":[]},{"mid":"","locale":"","description":"臺北市","score":0,"confidence":0,"topicality":0,"boundingPoly":{"vertices":[{"x":1213,"y":884},{"x":1379,"y":884},{"x":1379,"y":938},{"x":1213,"y":938}]},"locations":[],"properties":[]},{"mid":"","locale":"","description":"大安","score":0,"confidence":0,"topicality":0,"boundingPoly":{"vertices":[{"x":1386,"y":889},{"x":1497,"y":889},{"x":1497,"y":935},{"x":1386,"y":935}]},"locations":[],"properties":[]},{"mid":"","locale":"","description":"區","score":0,"confidence":0,"topicality":0,"boundingPoly":{"vertices":[{"x":1508,"y":886},{"x":1552,"y":886},{"x":1552,"y":935},{"x":1508,"y":935}]},"locations":[],"properties":[]},{"mid":"","locale":"","description":"建國","score":0,"confidence":0,"topicality":0,"boundingPoly":{"vertices":[{"x":1563,"y":886},{"x":1667,"y":886},{"x":1667,"y":935},{"x":1563,"y":935}]},"locations":[],"properties":[]},{"mid":"","locale":"","description":"南路","score":0,"confidence":0,"topicality":0,"boundingPoly":{"vertices":[{"x":1684,"y":884},{"x":1790,"y":884},{"x":1790,"y":935},{"x":1684,"y":935}]},"locations":[],"properties":[]},{"mid":"","locale":"","description":"二段","score":0,"confidence":0,"topicality":0,"boundingPoly":{"vertices":[{"x":1796,"y":887},{"x":1910,"y":887},{"x":1910,"y":934},{"x":1796,"y":934}]},"locations":[],"properties":[]},{"mid":"","locale":"","description":"69","score":0,"confidence":0,"topicality":0,"boundingPoly":{"vertices":[{"x":1926,"y":886},{"x":1982,"y":886},{"x":1982,"y":930},{"x":1926,"y":930}]},"locations":[],"properties":[]},{"mid":"","locale":"","description":"巷","score":0,"confidence":0,"topicality":0,"boundingPoly":{"vertices":[{"x":2001,"y":886},{"x":2055,"y":886},{"x":2055,"y":935},{"x":2001,"y":935}]},"locations":[],"properties":[]},{"mid":"","locale":"","description":",","score":0,"confidence":0,"topicality":0,"boundingPoly":{"vertices":[{"x":2080,"y":901},{"x":2090,"y":901},{"x":2090,"y":918},{"x":2080,"y":918}]},"locations":[],"properties":[]},{"mid":"","locale":"","description":"信義","score":0,"confidence":0,"topicality":0,"boundingPoly":{"vertices":[{"x":807,"y":1035},{"x":916,"y":1035},{"x":916,"y":1089},{"x":807,"y":1089}]},"locations":[],"properties":[]},{"mid":"","locale":"","description":"路三段","score":0,"confidence":0,"topicality":0,"boundingPoly":{"vertices":[{"x":923,"y":1040},{"x":1097,"y":1040},{"x":1097,"y":1086},{"x":923,"y":1086}]},"locations":[],"properties":[]},{"mid":"","locale":"","description":"134","score":0,"confidence":0,"topicality":0,"boundingPoly":{"vertices":[{"x":1120,"y":1038},{"x":1202,"y":1038},{"x":1202,"y":1084},{"x":1120,"y":1084}]},"locations":[],"properties":[]},{"mid":"","locale":"","description":"巷","score":0,"confidence":0,"topicality":0,"boundingPoly":{"vertices":[{"x":1221,"y":1036},{"x":1272,"y":1036},{"x":1272,"y":1089},{"x":1221,"y":1089}]},"locations":[],"properties":[]},{"mid":"","locale":"","description":"及","score":0,"confidence":0,"topicality":0,"boundingPoly":{"vertices":[{"x":1280,"y":1040},{"x":1333,"y":1040},{"x":1333,"y":1084},{"x":1280,"y":1084}]},"locations":[],"properties":[]},{"mid":"","locale":"","description":"建國","score":0,"confidence":0,"topicality":0,"boundingPoly":{"vertices":[{"x":1338,"y":1038},{"x":1444,"y":1038},{"x":1444,"y":1089},{"x":1338,"y":1089}]},"locations":[],"properties":[]},{"mid":"","locale":"","description":"南路","score":0,"confidence":0,"topicality":0,"boundingPoly":{"vertices":[{"x":1461,"y":1036},{"x":1567,"y":1036},{"x":1567,"y":1087},{"x":1461,"y":1087}]},"locations":[],"properties":[]},{"mid":"","locale":"","description":"二段","score":0,"confidence":0,"topicality":0,"boundingPoly":{"vertices":[{"x":1571,"y":1038},{"x":1685,"y":1038},{"x":1685,"y":1085},{"x":1571,"y":1085}]},"locations":[],"properties":[]},{"mid":"","locale":"","description":"所","score":0,"confidence":0,"topicality":0,"boundingPoly":{"vertices":[{"x":1688,"y":1040},{"x":1741,"y":1040},{"x":1741,"y":1084},{"x":1688,"y":1084}]},"locations":[],"properties":[]},{"mid":"","locale":"","description":"圍","score":0,"confidence":0,"topicality":0,"boundingPoly":{"vertices":[{"x":1751,"y":1036},{"x":1797,"y":1036},{"x":1797,"y":1087},{"x":1751,"y":1087}]},"locations":[],"properties":[]},{"mid":"","locale":"","description":"街廓","score":0,"confidence":0,"topicality":0,"boundingPoly":{"vertices":[{"x":1808,"y":1036},{"x":1917,"y":1036},{"x":1917,"y":1089},{"x":1808,"y":1089}]},"locations":[],"properties":[]},{"mid":"","locale":"","description":"內","score":0,"confidence":0,"topicality":0,"boundingPoly":{"vertices":[{"x":1929,"y":1042},{"x":1971,"y":1042},{"x":1971,"y":1086},{"x":1929,"y":1086}]},"locations":[],"properties":[]},{"mid":"","locale":"","description":"之","score":0,"confidence":0,"topicality":0,"boundingPoly":{"vertices":[{"x":1982,"y":1045},{"x":2036,"y":1045},{"x":2036,"y":1084},{"x":1982,"y":1084}]},"locations":[],"properties":[]},{"mid":"","locale":"","description":"東","score":0,"confidence":0,"topicality":0,"boundingPoly":{"vertices":[{"x":2044,"y":1036},{"x":2095,"y":1036},{"x":2095,"y":1089},{"x":2044,"y":1089}]},"locations":[],"properties":[]},{"mid":"","locale":"","description":"二","score":0,"confidence":0,"topicality":0,"boundingPoly":{"vertices":[{"x":411,"y":1348},{"x":465,"y":1348},{"x":465,"y":1380},{"x":411,"y":1380}]},"locations":[],"properties":[]},{"mid":"","locale":"","description":"、","score":0,"confidence":0,"topicality":0,"boundingPoly":{"vertices":[{"x":488,"y":1355},{"x":505,"y":1355},{"x":505,"y":1370},{"x":488,"y":1370}]},"locations":[],"properties":[]},{"mid":"","locale":"","description":"計畫","score":0,"confidence":0,"topicality":0,"boundingPoly":{"vertices":[{"x":529,"y":1340},{"x":636,"y":1340},{"x":636,"y":1391},{"x":529,"y":1391}]},"locations":[],"properties":[]},{"mid":"","locale":"","description":"範圍","score":0,"confidence":0,"topicality":0,"boundingPoly":{"vertices":[{"x":646,"y":1336},{"x":753,"y":1336},{"x":753,"y":1389},{"x":646,"y":1389}]},"locations":[],"properties":[]},{"mid":"","locale":"","description":":","score":0,"confidence":0,"topicality":0,"boundingPoly":{"vertices":[{"x":783,"y":1343},{"x":796,"y":1343},{"x":796,"y":1375},{"x":783,"y":1375}]},"locations":[],"properties":[]},{"mid":"","locale":"","description":"臺北市","score":0,"confidence":0,"topicality":0,"boundingPoly":{"vertices":[{"x":826,"y":1336},{"x":990,"y":1336},{"x":990,"y":1390},{"x":826,"y":1390}]},"locations":[],"properties":[]},{"mid":"","locale":"","description":"大安","score":0,"confidence":0,"topicality":0,"boundingPoly":{"vertices":[{"x":1000,"y":1341},{"x":1109,"y":1341},{"x":1109,"y":1388},{"x":1000,"y":1388}]},"locations":[],"properties":[]},{"mid":"","locale":"","description":"區","score":0,"confidence":0,"topicality":0,"boundingPoly":{"vertices":[{"x":1120,"y":1340},{"x":1167,"y":1340},{"x":1167,"y":1387},{"x":1120,"y":1387}]},"locations":[],"properties":[]},{"mid":"","locale":"","description":"瑞安","score":0,"confidence":0,"topicality":0,"boundingPoly":{"vertices":[{"x":1177,"y":1340},{"x":1286,"y":1340},{"x":1286,"y":1389},{"x":1177,"y":1389}]},"locations":[],"properties":[]},{"mid":"","locale":"","description":"段","score":0,"confidence":0,"topicality":0,"boundingPoly":{"vertices":[{"x":1292,"y":1340},{"x":1350,"y":1340},{"x":1350,"y":1387},{"x":1292,"y":1387}]},"locations":[],"properties":[]},{"mid":"","locale":"","description":"一小段","score":0,"confidence":0,"topicality":0,"boundingPoly":{"vertices":[{"x":1355,"y":1340},{"x":1524,"y":1340},{"x":1524,"y":1389},{"x":1355,"y":1389}]},"locations":[],"properties":[]},{"mid":"","locale":"","description":"221-3","score":0,"confidence":0,"topicality":0,"boundingPoly":{"vertices":[{"x":1540,"y":1338},{"x":1671,"y":1338},{"x":1671,"y":1384},{"x":1540,"y":1384}]},"locations":[],"properties":[]},{"mid":"","locale":"","description":",","score":0,"confidence":0,"topicality":0,"boundingPoly":{"vertices":[{"x":1696,"y":1357},{"x":1713,"y":1357},{"x":1713,"y":1370},{"x":1696,"y":1370}]},"locations":[],"properties":[]},{"mid":"","locale":"","description":"225、226","score":0,"confidence":0,"topicality":0,"boundingPoly":{"vertices":[{"x":1734,"y":1338},{"x":1970,"y":1338},{"x":1970,"y":1382},{"x":1734,"y":1382}]},"locations":[],"properties":[]},{"mid":"","locale":"","description":"地","score":0,"confidence":0,"topicality":0,"boundingPoly":{"vertices":[{"x":1986,"y":1340},{"x":2042,"y":1340},{"x":2042,"y":1386},{"x":1986,"y":1386}]},"locations":[],"properties":[]},{"mid":"","locale":"","description":"號","score":0,"confidence":0,"topicality":0,"boundingPoly":{"vertices":[{"x":2048,"y":1340},{"x":2101,"y":1340},{"x":2101,"y":1389},{"x":2048,"y":1389}]},"locations":[],"properties":[]},{"mid":"","locale":"","description":"等","score":0,"confidence":0,"topicality":0,"boundingPoly":{"vertices":[{"x":807,"y":1487},{"x":855,"y":1488},{"x":854,"y":1541},{"x":806,"y":1540}]},"locations":[],"properties":[]},{"mid":"","locale":"","description":"3","score":0,"confidence":0,"topicality":0,"boundingPoly":{"vertices":[{"x":874,"y":1489},{"x":896,"y":1489},{"x":895,"y":1534},{"x":873,"y":1534}]},"locations":[],"properties":[]},{"mid":"","locale":"","description":"筆","score":0,"confidence":0,"topicality":0,"boundingPoly":{"vertices":[{"x":923,"y":1489},{"x":969,"y":1490},{"x":968,"y":1538},{"x":922,"y":1537}]},"locations":[],"properties":[]},{"mid":"","locale":"","description":"土地","score":0,"confidence":0,"topicality":0,"boundingPoly":{"vertices":[{"x":980,"y":1491},{"x":1092,"y":1492},{"x":1091,"y":1537},{"x":979,"y":1536}]},"locations":[],"properties":[]},{"mid":"","locale":"","description":"。","score":0,"confidence":0,"topicality":0,"boundingPoly":{"vertices":[{"x":1115,"y":1506},{"x":1129,"y":1506},{"x":1129,"y":1520},{"x":1115,"y":1520}]},"locations":[],"properties":[]},{"mid":"","locale":"","description":"三","score":0,"confidence":0,"topicality":0,"boundingPoly":{"vertices":[{"x":411,"y":1645},{"x":465,"y":1645},{"x":465,"y":1686},{"x":411,"y":1686}]},"locations":[],"properties":[]},{"mid":"","locale":"","description":"、","score":0,"confidence":0,"topicality":0,"boundingPoly":{"vertices":[{"x":490,"y":1657},{"x":507,"y":1657},{"x":507,"y":1672},{"x":490,"y":1672}]},"locations":[],"properties":[]},{"mid":"","locale":"","description":"計畫","score":0,"confidence":0,"topicality":0,"boundingPoly":{"vertices":[{"x":527,"y":1638},{"x":638,"y":1638},{"x":638,"y":1692},{"x":527,"y":1692}]},"locations":[],"properties":[]},{"mid":"","locale":"","description":"面積","score":0,"confidence":0,"topicality":0,"boundingPoly":{"vertices":[{"x":649,"y":1641},{"x":756,"y":1641},{"x":756,"y":1690},{"x":649,"y":1690}]},"locations":[],"properties":[]},{"mid":"","locale":"","description":":","score":0,"confidence":0,"topicality":0,"boundingPoly":{"vertices":[{"x":784,"y":1645},{"x":795,"y":1645},{"x":795,"y":1677},{"x":784,"y":1677}]},"locations":[],"properties":[]},{"mid":"","locale":"","description":"1,228","score":0,"confidence":0,"topicality":0,"boundingPoly":{"vertices":[{"x":826,"y":1640},{"x":949,"y":1640},{"x":949,"y":1693},{"x":826,"y":1693}]},"locations":[],"properties":[]},{"mid":"","locale":"","description":"平方公尺","score":0,"confidence":0,"topicality":0,"boundingPoly":{"vertices":[{"x":970,"y":1638},{"x":1203,"y":1638},{"x":1203,"y":1691},{"x":970,"y":1691}]},"locations":[],"properties":[]},{"mid":"","locale":"","description":"。","score":0,"confidence":0,"topicality":0,"boundingPoly":{"vertices":[{"x":1225,"y":1657},{"x":1240,"y":1657},{"x":1240,"y":1672},{"x":1225,"y":1672}]},"locations":[],"properties":[]},{"mid":"","locale":"","description":"四","score":0,"confidence":0,"topicality":0,"boundingPoly":{"vertices":[{"x":416,"y":1801},{"x":462,"y":1801},{"x":462,"y":1833},{"x":416,"y":1833}]},"locations":[],"properties":[]},{"mid":"","locale":"","description":"、","score":0,"confidence":0,"topicality":0,"boundingPoly":{"vertices":[{"x":486,"y":1806},{"x":503,"y":1806},{"x":503,"y":1821},{"x":486,"y":1821}]},"locations":[],"properties":[]},{"mid":"","locale":"","description":"法令","score":0,"confidence":0,"topicality":0,"boundingPoly":{"vertices":[{"x":524,"y":1790},{"x":631,"y":1790},{"x":631,"y":1839},{"x":524,"y":1839}]},"locations":[],"properties":[]},{"mid":"","locale":"","description":"依據","score":0,"confidence":0,"topicality":0,"boundingPoly":{"vertices":[{"x":640,"y":1789},{"x":753,"y":1789},{"x":753,"y":1840},{"x":640,"y":1840}]},"locations":[],"properties":[]},{"mid":"","locale":"","description":":","score":0,"confidence":0,"topicality":0,"boundingPoly":{"vertices":[{"x":774,"y":1796},{"x":785,"y":1796},{"x":785,"y":1828},{"x":774,"y":1828}]},"locations":[],"properties":[]},{"mid":"","locale":"","description":"都市","score":0,"confidence":0,"topicality":0,"boundingPoly":{"vertices":[{"x":808,"y":1792},{"x":919,"y":1792},{"x":919,"y":1841},{"x":808,"y":1841}]},"locations":[],"properties":[]},{"mid":"","locale":"","description":"更新","score":0,"confidence":0,"topicality":0,"boundingPoly":{"vertices":[{"x":928,"y":1790},{"x":1035,"y":1790},{"x":1035,"y":1841},{"x":928,"y":1841}]},"locations":[],"properties":[]},{"mid":"","locale":"","description":"條例","score":0,"confidence":0,"topicality":0,"boundingPoly":{"vertices":[{"x":1045,"y":1792},{"x":1154,"y":1792},{"x":1154,"y":1841},{"x":1045,"y":1841}]},"locations":[],"properties":[]},{"mid":"","locale":"","description":"第","score":0,"confidence":0,"topicality":0,"boundingPoly":{"vertices":[{"x":1168,"y":1789},{"x":1210,"y":1789},{"x":1210,"y":1840},{"x":1168,"y":1840}]},"locations":[],"properties":[]},{"mid":"","locale":"","description":"11","score":0,"confidence":0,"topicality":0,"boundingPoly":{"vertices":[{"x":1240,"y":1792},{"x":1282,"y":1792},{"x":1282,"y":1836},{"x":1240,"y":1836}]},"locations":[],"properties":[]},{"mid":"","locale":"","description":"條","score":0,"confidence":0,"topicality":0,"boundingPoly":{"vertices":[{"x":1305,"y":1792},{"x":1359,"y":1792},{"x":1359,"y":1838},{"x":1305,"y":1838}]},"locations":[],"properties":[]},{"mid":"","locale":"","description":"及","score":0,"confidence":0,"topicality":0,"boundingPoly":{"vertices":[{"x":1365,"y":1792},{"x":1418,"y":1792},{"x":1418,"y":1836},{"x":1365,"y":1836}]},"locations":[],"properties":[]},{"mid":"","locale":"","description":"臺北市","score":0,"confidence":0,"topicality":0,"boundingPoly":{"vertices":[{"x":1429,"y":1789},{"x":1593,"y":1789},{"x":1593,"y":1842},{"x":1429,"y":1842}]},"locations":[],"properties":[]},{"mid":"","locale":"","description":"都市","score":0,"confidence":0,"topicality":0,"boundingPoly":{"vertices":[{"x":1599,"y":1792},{"x":1708,"y":1792},{"x":1708,"y":1841},{"x":1599,"y":1841}]},"locations":[],"properties":[]},{"mid":"","locale":"","description":"更新","score":0,"confidence":0,"topicality":0,"boundingPoly":{"vertices":[{"x":1720,"y":1790},{"x":1826,"y":1790},{"x":1826,"y":1841},{"x":1720,"y":1841}]},"locations":[],"properties":[]},{"mid":"","locale":"","description":"自治","score":0,"confidence":0,"topicality":0,"boundingPoly":{"vertices":[{"x":1842,"y":1790},{"x":1943,"y":1790},{"x":1943,"y":1837},{"x":1842,"y":1837}]},"locations":[],"properties":[]},{"mid":"","locale":"","description":"條例","score":0,"confidence":0,"topicality":0,"boundingPoly":{"vertices":[{"x":1952,"y":1792},{"x":2059,"y":1792},{"x":2059,"y":1839},{"x":1952,"y":1839}]},"locations":[],"properties":[]},{"mid":"","locale":"","description":"第","score":0,"confidence":0,"topicality":0,"boundingPoly":{"vertices":[{"x":2072,"y":1789},{"x":2114,"y":1789},{"x":2114,"y":1840},{"x":2072,"y":1840}]},"locations":[],"properties":[]},{"mid":"","locale":"","description":"15","score":0,"confidence":0,"topicality":0,"boundingPoly":{"vertices":[{"x":807,"y":1940},{"x":857,"y":1940},{"x":857,"y":1985},{"x":807,"y":1985}]},"locations":[],"properties":[]},{"mid":"","locale":"","description":"條","score":0,"confidence":0,"topicality":0,"boundingPoly":{"vertices":[{"x":877,"y":1940},{"x":927,"y":1940},{"x":927,"y":1988},{"x":877,"y":1988}]},"locations":[],"properties":[]},{"mid":"","locale":"","description":"。","score":0,"confidence":0,"topicality":0,"boundingPoly":{"vertices":[{"x":951,"y":1957},{"x":967,"y":1957},{"x":967,"y":1969},{"x":951,"y":1969}]},"locations":[],"properties":[]},{"mid":"","locale":"","description":"厅","score":0,"confidence":0,"topicality":0,"boundingPoly":{"vertices":[{"x":2106,"y":2140},{"x":2135,"y":2140},{"x":2135,"y":2179},{"x":2106,"y":2179}]},"locations":[],"properties":[]},{"mid":"","locale":"","description":"企","score":0,"confidence":0,"topicality":0,"boundingPoly":{"vertices":[{"x":1789,"y":3168},{"x":1830,"y":3170},{"x":1828,"y":3211},{"x":1787,"y":3209}]},"locations":[],"properties":[]}],"fullTextAnnotation":{"pages":[{"property":{"detectedLanguages":[{"languageCode":"zh-Hant","confidence":0}],"detectedBreak":null},"width":2482,"height":3510,"blocks":[{"property":{"detectedLanguages":[{"languageCode":"zh-Hant","confidence":0}],"detectedBreak":null},"boundingBox":{"vertices":[{"x":449,"y":373},{"x":2123,"y":373},{"x":2123,"y":429},{"x":449,"y":429}]},"paragraphs":[{"property":{"detectedLanguages":[{"languageCode":"zh-Hant","confidence":0}],"detectedBreak":null},"boundingBox":{"vertices":[{"x":449,"y":373},{"x":2123,"y":373},{"x":2123,"y":429},{"x":449,"y":429}]},"words":[{"property":{"detectedLanguages":[{"languageCode":"zh-Hans","confidence":0}],"detectedBreak":null},"boundingBox":{"vertices":[{"x":449,"y":375},{"x":493,"y":375},{"x":493,"y":428},{"x":449,"y":428}]},"symbols":[{"property":{"detectedLanguages":[{"languageCode":"zh-Hant","confidence":0}],"detectedBreak":null},"boundingBox":{"vertices":[{"x":449,"y":375},{"x":493,"y":375},{"x":493,"y":428},{"x":449,"y":428}]},"text":"案"}]},{"property":{"detectedLanguages":[{"languageCode":"ja","confidence":0}],"detectedBreak":null},"boundingBox":{"vertices":[{"x":500,"y":377},{"x":547,"y":377},{"x":547,"y":426},{"x":500,"y":426}]},"symbols":[{"property":{"detectedLanguages":[{"languageCode":"zh-Hant","confidence":0}],"detectedBreak":null},"boundingBox":{"vertices":[{"x":500,"y":377},{"x":547,"y":377},{"x":547,"y":426},{"x":500,"y":426}]},"text":"名"}]},{"property":{"detectedLanguages":[{"languageCode":"en","confidence":0}],"detectedBreak":null},"boundingBox":{"vertices":[{"x":574,"y":380},{"x":587,"y":380},{"x":587,"y":414},{"x":574,"y":414}]},"symbols":[{"property":{"detectedLanguages":[{"languageCode":"zh-Hant","confidence":0}],"detectedBreak":null},"boundingBox":{"vertices":[{"x":574,"y":380},{"x":587,"y":380},{"x":587,"y":414},{"x":574,"y":414}]},"text":":"}]},{"property":{"detectedLanguages":[{"languageCode":"zh-Hant","confidence":0}],"detectedBreak":null},"boundingBox":{"vertices":[{"x":610,"y":375},{"x":719,"y":375},{"x":719,"y":429},{"x":610,"y":429}]},"symbols":[{"property":{"detectedLanguages":[{"languageCode":"zh-Hant","confidence":0}],"detectedBreak":null},"boundingBox":{"vertices":[{"x":610,"y":375},{"x":657,"y":375},{"x":657,"y":429},{"x":610,"y":429}]},"text":"劃"},{"property":{"detectedLanguages":[{"languageCode":"zh-Hant","confidence":0}],"detectedBreak":null},"boundingBox":{"vertices":[{"x":668,"y":378},{"x":719,"y":378},{"x":719,"y":427},{"x":668,"y":427}]},"text":"定"}]},{"property":{"detectedLanguages":[{"languageCode":"zh-Hant","confidence":0}],"detectedBreak":null},"boundingBox":{"vertices":[{"x":728,"y":373},{"x":895,"y":373},{"x":895,"y":429},{"x":728,"y":429}]},"symbols":[{"property":{"detectedLanguages":[{"languageCode":"zh-Hant","confidence":0}],"detectedBreak":null},"boundingBox":{"vertices":[{"x":728,"y":373},{"x":779,"y":373},{"x":779,"y":429},{"x":728,"y":429}]},"text":"臺"},{"property":{"detectedLanguages":[{"languageCode":"zh-Hant","confidence":0}],"detectedBreak":null},"boundingBox":{"vertices":[{"x":786,"y":378},{"x":839,"y":378},{"x":839,"y":425},{"x":786,"y":425}]},"text":"北"},{"property":{"detectedLanguages":[{"languageCode":"zh-Hant","confidence":0}],"detectedBreak":null},"boundingBox":{"vertices":[{"x":844,"y":377},{"x":895,"y":377},{"x":895,"y":430},{"x":844,"y":430}]},"text":"市"}]},{"property":{"detectedLanguages":[{"languageCode":"ja","confidence":0}],"detectedBreak":null},"boundingBox":{"vertices":[{"x":901,"y":378},{"x":1015,"y":378},{"x":1015,"y":427},{"x":901,"y":427}]},"symbols":[{"property":{"detectedLanguages":[{"languageCode":"zh-Hant","confidence":0}],"detectedBreak":null},"boundingBox":{"vertices":[{"x":901,"y":378},{"x":955,"y":378},{"x":955,"y":425},{"x":901,"y":425}]},"text":"大"},{"property":{"detectedLanguages":[{"languageCode":"zh-Hant","confidence":0}],"detectedBreak":null},"boundingBox":{"vertices":[{"x":959,"y":378},{"x":1015,"y":378},{"x":1015,"y":427},{"x":959,"y":427}]},"text":"安"}]},{"property":{"detectedLanguages":[{"languageCode":"zh-Hant","confidence":0}],"detectedBreak":null},"boundingBox":{"vertices":[{"x":1023,"y":377},{"x":1070,"y":377},{"x":1070,"y":426},{"x":1023,"y":426}]},"symbols":[{"property":{"detectedLanguages":[{"languageCode":"zh-Hant","confidence":0}],"detectedBreak":null},"boundingBox":{"vertices":[{"x":1023,"y":377},{"x":1070,"y":377},{"x":1070,"y":426},{"x":1023,"y":426}]},"text":"區"}]},{"property":{"detectedLanguages":[{"languageCode":"zh-Hans","confidence":0}],"detectedBreak":null},"boundingBox":{"vertices":[{"x":1079,"y":378},{"x":1192,"y":378},{"x":1192,"y":429},{"x":1079,"y":429}]},"symbols":[{"property":{"detectedLanguages":[{"languageCode":"zh-Hant","confidence":0}],"detectedBreak":null},"boundingBox":{"vertices":[{"x":1079,"y":378},{"x":1132,"y":378},{"x":1132,"y":429},{"x":1079,"y":429}]},"text":"瑞"},{"property":{"detectedLanguages":[{"languageCode":"zh-Hant","confidence":0}],"detectedBreak":null},"boundingBox":{"vertices":[{"x":1139,"y":378},{"x":1192,"y":378},{"x":1192,"y":427},{"x":1139,"y":427}]},"text":"安"}]},{"property":{"detectedLanguages":[{"languageCode":"zh-Hans","confidence":0}],"detectedBreak":null},"boundingBox":{"vertices":[{"x":1196,"y":377},{"x":1255,"y":377},{"x":1255,"y":426},{"x":1196,"y":426}]},"symbols":[{"property":{"detectedLanguages":[{"languageCode":"zh-Hant","confidence":0}],"detectedBreak":null},"boundingBox":{"vertices":[{"x":1196,"y":377},{"x":1255,"y":377},{"x":1255,"y":426},{"x":1196,"y":426}]},"text":"段"}]},{"property":{"detectedLanguages":[{"languageCode":"zh-Hans","confidence":0}],"detectedBreak":null},"boundingBox":{"vertices":[{"x":1259,"y":377},{"x":1430,"y":377},{"x":1430,"y":428},{"x":1259,"y":428}]},"symbols":[{"property":{"detectedLanguages":[{"languageCode":"zh-Hant","confidence":0}],"detectedBreak":null},"boundingBox":{"vertices":[{"x":1259,"y":395},{"x":1306,"y":395},{"x":1306,"y":406},{"x":1259,"y":406}]},"text":"一"},{"property":{"detectedLanguages":[{"languageCode":"zh-Hant","confidence":0}],"detectedBreak":null},"boundingBox":{"vertices":[{"x":1316,"y":378},{"x":1367,"y":378},{"x":1367,"y":427},{"x":1316,"y":427}]},"text":"小"},{"property":{"detectedLanguages":[{"languageCode":"zh-Hant","confidence":0}],"detectedBreak":null},"boundingBox":{"vertices":[{"x":1372,"y":377},{"x":1430,"y":377},{"x":1430,"y":426},{"x":1372,"y":426}]},"text":"段"}]},{"property":{"detectedLanguages":[{"languageCode":"en","confidence":0}],"detectedBreak":null},"boundingBox":{"vertices":[{"x":1446,"y":378},{"x":1579,"y":378},{"x":1579,"y":420},{"x":1446,"y":420}]},"symbols":[{"property":{"detectedLanguages":[{"languageCode":"zh-Hant","confidence":0}],"detectedBreak":null},"boundingBox":{"vertices":[{"x":1446,"y":378},{"x":1471,"y":378},{"x":1471,"y":420},{"x":1446,"y":420}]},"text":"2"},{"property":{"detectedLanguages":[{"languageCode":"zh-Hant","confidence":0}],"detectedBreak":null},"boundingBox":{"vertices":[{"x":1475,"y":378},{"x":1500,"y":378},{"x":1500,"y":420},{"x":1475,"y":420}]},"text":"2"},{"property":{"detectedLanguages":[{"languageCode":"zh-Hant","confidence":0}],"detectedBreak":null},"boundingBox":{"vertices":[{"x":1503,"y":378},{"x":1526,"y":378},{"x":1526,"y":420},{"x":1503,"y":420}]},"text":"1"},{"property":{"detectedLanguages":[{"languageCode":"zh-Hant","confidence":0}],"detectedBreak":null},"boundingBox":{"vertices":[{"x":1533,"y":378},{"x":1553,"y":378},{"x":1553,"y":420},{"x":1533,"y":420}]},"text":"-"},{"property":{"detectedLanguages":[{"languageCode":"zh-Hant","confidence":0}],"detectedBreak":null},"boundingBox":{"vertices":[{"x":1556,"y":378},{"x":1579,"y":378},{"x":1579,"y":420},{"x":1556,"y":420}]},"text":"3"}]},{"property":{"detectedLanguages":[{"languageCode":"ja","confidence":0}],"detectedBreak":null},"boundingBox":{"vertices":[{"x":1597,"y":375},{"x":1655,"y":375},{"x":1655,"y":424},{"x":1597,"y":424}]},"symbols":[{"property":{"detectedLanguages":[{"languageCode":"zh-Hant","confidence":0}],"detectedBreak":null},"boundingBox":{"vertices":[{"x":1597,"y":375},{"x":1655,"y":375},{"x":1655,"y":424},{"x":1597,"y":424}]},"text":"地"}]},{"property":{"detectedLanguages":[{"languageCode":"zh-Hant","confidence":0}],"detectedBreak":null},"boundingBox":{"vertices":[{"x":1659,"y":377},{"x":1713,"y":377},{"x":1713,"y":426},{"x":1659,"y":426}]},"symbols":[{"property":{"detectedLanguages":[{"languageCode":"zh-Hant","confidence":0}],"detectedBreak":null},"boundingBox":{"vertices":[{"x":1659,"y":377},{"x":1713,"y":377},{"x":1713,"y":426},{"x":1659,"y":426}]},"text":"號"}]},{"property":{"detectedLanguages":[{"languageCode":"ja","confidence":0}],"detectedBreak":null},"boundingBox":{"vertices":[{"x":1720,"y":373},{"x":1766,"y":373},{"x":1766,"y":429},{"x":1720,"y":429}]},"symbols":[{"property":{"detectedLanguages":[{"languageCode":"zh-Hant","confidence":0}],"detectedBreak":null},"boundingBox":{"vertices":[{"x":1720,"y":373},{"x":1766,"y":373},{"x":1766,"y":429},{"x":1720,"y":429}]},"text":"等"}]},{"property":{"detectedLanguages":[{"languageCode":"en","confidence":0}],"detectedBreak":null},"boundingBox":{"vertices":[{"x":1785,"y":378},{"x":1812,"y":378},{"x":1812,"y":420},{"x":1785,"y":420}]},"symbols":[{"property":{"detectedLanguages":[{"languageCode":"zh-Hant","confidence":0}],"detectedBreak":null},"boundingBox":{"vertices":[{"x":1785,"y":378},{"x":1812,"y":378},{"x":1812,"y":420},{"x":1785,"y":420}]},"text":"3"}]},{"property":{"detectedLanguages":[{"languageCode":"zh-Hant","confidence":0}],"detectedBreak":null},"boundingBox":{"vertices":[{"x":1838,"y":373},{"x":1885,"y":373},{"x":1885,"y":420},{"x":1838,"y":420}]},"symbols":[{"property":{"detectedLanguages":[{"languageCode":"zh-Hant","confidence":0}],"detectedBreak":null},"boundingBox":{"vertices":[{"x":1838,"y":373},{"x":1885,"y":373},{"x":1885,"y":420},{"x":1838,"y":420}]},"text":"筆"}]},{"property":{"detectedLanguages":[{"languageCode":"ja","confidence":0}],"detectedBreak":null},"boundingBox":{"vertices":[{"x":1893,"y":377},{"x":2006,"y":377},{"x":2006,"y":424},{"x":1893,"y":424}]},"symbols":[{"property":{"detectedLanguages":[{"languageCode":"zh-Hant","confidence":0}],"detectedBreak":null},"boundingBox":{"vertices":[{"x":1893,"y":377},{"x":1944,"y":377},{"x":1944,"y":423},{"x":1893,"y":423}]},"text":"土"},{"property":{"detectedLanguages":[{"languageCode":"zh-Hant","confidence":0}],"detectedBreak":null},"boundingBox":{"vertices":[{"x":1952,"y":377},{"x":2006,"y":377},{"x":2006,"y":424},{"x":1952,"y":424}]},"text":"地"}]},{"property":{"detectedLanguages":[{"languageCode":"zh-Hant","confidence":0}],"detectedBreak":null},"boundingBox":{"vertices":[{"x":2013,"y":375},{"x":2060,"y":375},{"x":2060,"y":429},{"x":2013,"y":429}]},"symbols":[{"property":{"detectedLanguages":[{"languageCode":"zh-Hant","confidence":0}],"detectedBreak":null},"boundingBox":{"vertices":[{"x":2013,"y":375},{"x":2060,"y":375},{"x":2060,"y":429},{"x":2013,"y":429}]},"text":"為"}]},{"property":{"detectedLanguages":[{"languageCode":"ja","confidence":0}],"detectedBreak":null},"boundingBox":{"vertices":[{"x":2072,"y":377},{"x":2123,"y":377},{"x":2123,"y":430},{"x":2072,"y":430}]},"symbols":[{"property":{"detectedLanguages":[{"languageCode":"zh-Hant","confidence":0}],"detectedBreak":{"type":"EOL_SURE_SPACE","isPrefix":false}},"boundingBox":{"vertices":[{"x":2072,"y":377},{"x":2123,"y":377},{"x":2123,"y":430},{"x":2072,"y":430}]},"text":"更"}]}]}],"blockType":"TEXT"},{"property":{"detectedLanguages":[{"languageCode":"zh-Hant","confidence":0}],"detectedBreak":null},"boundingBox":{"vertices":[{"x":582,"y":522},{"x":927,"y":524},{"x":927,"y":579},{"x":582,"y":577}]},"paragraphs":[{"property":{"detectedLanguages":[{"languageCode":"zh-Hant","confidence":0}],"detectedBreak":null},"boundingBox":{"vertices":[{"x":582,"y":522},{"x":928,"y":522},{"x":928,"y":581},{"x":582,"y":581}]},"words":[{"property":{"detectedLanguages":[{"languageCode":"zh-Hans","confidence":0}],"detectedBreak":null},"boundingBox":{"vertices":[{"x":582,"y":526},{"x":634,"y":526},{"x":634,"y":572},{"x":582,"y":572}]},"symbols":[{"property":{"detectedLanguages":[{"languageCode":"zh-Hant","confidence":0}],"detectedBreak":null},"boundingBox":{"vertices":[{"x":582,"y":526},{"x":634,"y":526},{"x":634,"y":572},{"x":582,"y":572}]},"text":"新"}]},{"property":{"detectedLanguages":[{"languageCode":"zh-Hant","confidence":0}],"detectedBreak":null},"boundingBox":{"vertices":[{"x":642,"y":522},{"x":752,"y":523},{"x":752,"y":578},{"x":642,"y":577}]},"symbols":[{"property":{"detectedLanguages":[{"languageCode":"zh-Hant","confidence":0}],"detectedBreak":null},"boundingBox":{"vertices":[{"x":642,"y":522},{"x":690,"y":522},{"x":690,"y":577},{"x":642,"y":577}]},"text":"單"},{"property":{"detectedLanguages":[{"languageCode":"zh-Hant","confidence":0}],"detectedBreak":null},"boundingBox":{"vertices":[{"x":700,"y":527},{"x":752,"y":527},{"x":752,"y":572},{"x":700,"y":572}]},"text":"元"}]},{"property":{"detectedLanguages":[{"languageCode":"zh-Hant","confidence":0}],"detectedBreak":null},"boundingBox":{"vertices":[{"x":759,"y":524},{"x":927,"y":525},{"x":927,"y":580},{"x":759,"y":579}]},"symbols":[{"property":{"detectedLanguages":[{"languageCode":"zh-Hant","confidence":0}],"detectedBreak":null},"boundingBox":{"vertices":[{"x":759,"y":527},{"x":812,"y":527},{"x":812,"y":573},{"x":759,"y":573}]},"text":"檢"},{"property":{"detectedLanguages":[{"languageCode":"zh-Hant","confidence":0}],"detectedBreak":null},"boundingBox":{"vertices":[{"x":819,"y":527},{"x":871,"y":527},{"x":871,"y":577},{"x":819,"y":577}]},"text":"討"},{"property":{"detectedLanguages":[{"languageCode":"zh-Hant","confidence":0}],"detectedBreak":{"type":"EOL_SURE_SPACE","isPrefix":false}},"boundingBox":{"vertices":[{"x":880,"y":524},{"x":926,"y":524},{"x":926,"y":579},{"x":880,"y":579}]},"text":"書"}]}]}],"blockType":"TEXT"},{"property":{"detectedLanguages":[{"languageCode":"zh-Hant","confidence":0}],"detectedBreak":null},"boundingBox":{"vertices":[{"x":392,"y":731},{"x":792,"y":726},{"x":793,"y":784},{"x":393,"y":789}]},"paragraphs":[{"property":{"detectedLanguages":[{"languageCode":"zh-Hant","confidence":0}],"detectedBreak":null},"boundingBox":{"vertices":[{"x":392,"y":730},{"x":793,"y":730},{"x":793,"y":788},{"x":392,"y":788}]},"words":[{"property":{"detectedLanguages":[{"languageCode":"zh-Hant","confidence":0}],"detectedBreak":null},"boundingBox":{"vertices":[{"x":392,"y":731},{"x":558,"y":729},{"x":559,"y":784},{"x":393,"y":786}]},"symbols":[{"property":{"detectedLanguages":[{"languageCode":"zh-Hant","confidence":0}],"detectedBreak":null},"boundingBox":{"vertices":[{"x":392,"y":731},{"x":428,"y":731},{"x":429,"y":786},{"x":393,"y":786}]},"text":"申"},{"property":{"detectedLanguages":[{"languageCode":"zh-Hant","confidence":0}],"detectedBreak":null},"boundingBox":{"vertices":[{"x":442,"y":735},{"x":497,"y":734},{"x":498,"y":786},{"x":443,"y":787}]},"text":"請"},{"property":{"detectedLanguages":[{"languageCode":"zh-Hant","confidence":0}],"detectedBreak":null},"boundingBox":{"vertices":[{"x":503,"y":738},{"x":558,"y":737},{"x":559,"y":780},{"x":504,"y":781}]},"text":"人"}]},{"property":{"detectedLanguages":[{"languageCode":"en","confidence":0}],"detectedBreak":null},"boundingBox":{"vertices":[{"x":581,"y":738},{"x":593,"y":738},{"x":593,"y":771},{"x":581,"y":771}]},"symbols":[{"property":{"detectedLanguages":[{"languageCode":"zh-Hant","confidence":0}],"detectedBreak":null},"boundingBox":{"vertices":[{"x":581,"y":738},{"x":593,"y":738},{"x":593,"y":771},{"x":581,"y":771}]},"text":":"}]},{"property":{"detectedLanguages":[{"languageCode":"zh-Hant","confidence":0}],"detectedBreak":null},"boundingBox":{"vertices":[{"x":618,"y":735},{"x":791,"y":733},{"x":792,"y":785},{"x":619,"y":787}]},"symbols":[{"property":{"detectedLanguages":[{"languageCode":"zh-Hant","confidence":0}],"detectedBreak":null},"boundingBox":{"vertices":[{"x":618,"y":736},{"x":671,"y":735},{"x":672,"y":785},{"x":619,"y":786}]},"text":"趙"},{"property":{"detectedLanguages":[{"languageCode":"zh-Hant","confidence":0}],"detectedBreak":null},"boundingBox":{"vertices":[{"x":678,"y":740},{"x":728,"y":739},{"x":729,"y":780},{"x":679,"y":781}]},"text":"玉"},{"property":{"detectedLanguages":[{"languageCode":"zh-Hant","confidence":0}],"detectedBreak":{"type":"EOL_SURE_SPACE","isPrefix":false}},"boundingBox":{"vertices":[{"x":736,"y":733},{"x":791,"y":732},{"x":792,"y":784},{"x":737,"y":785}]},"text":"琴"}]}]}],"blockType":"TEXT"},{"property":{"detectedLanguages":[{"languageCode":"zh-Hant","confidence":0}],"detectedBreak":null},"boundingBox":{"vertices":[{"x":390,"y":884},{"x":2090,"y":884},{"x":2090,"y":938},{"x":390,"y":938}]},"paragraphs":[{"property":{"detectedLanguages":[{"languageCode":"zh-Hant","confidence":0}],"detectedBreak":null},"boundingBox":{"vertices":[{"x":390,"y":884},{"x":2090,"y":884},{"x":2090,"y":938},{"x":390,"y":938}]},"words":[{"property":{"detectedLanguages":[{"languageCode":"zh-Hans","confidence":0}],"detectedBreak":null},"boundingBox":{"vertices":[{"x":390,"y":904},{"x":436,"y":904},{"x":436,"y":914},{"x":390,"y":914}]},"symbols":[{"property":{"detectedLanguages":[{"languageCode":"zh-Hant","confidence":0}],"detectedBreak":null},"boundingBox":{"vertices":[{"x":390,"y":904},{"x":436,"y":904},{"x":436,"y":914},{"x":390,"y":914}]},"text":"一"}]},{"property":{"detectedLanguages":[{"languageCode":"en","confidence":0}],"detectedBreak":null},"boundingBox":{"vertices":[{"x":464,"y":903},{"x":479,"y":903},{"x":479,"y":918},{"x":464,"y":918}]},"symbols":[{"property":{"detectedLanguages":[{"languageCode":"zh-Hant","confidence":0}],"detectedBreak":null},"boundingBox":{"vertices":[{"x":464,"y":903},{"x":479,"y":903},{"x":479,"y":918},{"x":464,"y":918}]},"text":"、"}]},{"property":{"detectedLanguages":[{"languageCode":"zh-Hant","confidence":0}],"detectedBreak":null},"boundingBox":{"vertices":[{"x":503,"y":884},{"x":610,"y":884},{"x":610,"y":938},{"x":503,"y":938}]},"symbols":[{"property":{"detectedLanguages":[{"languageCode":"zh-Hant","confidence":0}],"detectedBreak":null},"boundingBox":{"vertices":[{"x":503,"y":887},{"x":554,"y":887},{"x":554,"y":938},{"x":503,"y":938}]},"text":"計"},{"property":{"detectedLanguages":[{"languageCode":"zh-Hant","confidence":0}],"detectedBreak":null},"boundingBox":{"vertices":[{"x":567,"y":884},{"x":611,"y":884},{"x":611,"y":938},{"x":567,"y":938}]},"text":"畫"}]},{"property":{"detectedLanguages":[{"languageCode":"zh-Hans","confidence":0}],"detectedBreak":null},"boundingBox":{"vertices":[{"x":622,"y":886},{"x":731,"y":886},{"x":731,"y":935},{"x":622,"y":935}]},"symbols":[{"property":{"detectedLanguages":[{"languageCode":"zh-Hant","confidence":0}],"detectedBreak":null},"boundingBox":{"vertices":[{"x":622,"y":891},{"x":675,"y":891},{"x":675,"y":932},{"x":622,"y":932}]},"text":"位"},{"property":{"detectedLanguages":[{"languageCode":"zh-Hant","confidence":0}],"detectedBreak":null},"boundingBox":{"vertices":[{"x":683,"y":886},{"x":730,"y":886},{"x":730,"y":935},{"x":683,"y":935}]},"text":"置"}]},{"property":{"detectedLanguages":[{"languageCode":"en","confidence":0}],"detectedBreak":null},"boundingBox":{"vertices":[{"x":757,"y":891},{"x":770,"y":891},{"x":770,"y":923},{"x":757,"y":923}]},"symbols":[{"property":{"detectedLanguages":[{"languageCode":"zh-Hant","confidence":0}],"detectedBreak":null},"boundingBox":{"vertices":[{"x":757,"y":891},{"x":770,"y":891},{"x":770,"y":923},{"x":757,"y":923}]},"text":":"}]},{"property":{"detectedLanguages":[{"languageCode":"ja","confidence":0}],"detectedBreak":null},"boundingBox":{"vertices":[{"x":798,"y":886},{"x":854,"y":886},{"x":854,"y":937},{"x":798,"y":937}]},"symbols":[{"property":{"detectedLanguages":[{"languageCode":"zh-Hant","confidence":0}],"detectedBreak":null},"boundingBox":{"vertices":[{"x":798,"y":886},{"x":854,"y":886},{"x":854,"y":937},{"x":798,"y":937}]},"text":"本"}]},{"property":{"detectedLanguages":[{"languageCode":"zh-Hans","confidence":0}],"detectedBreak":null},"boundingBox":{"vertices":[{"x":860,"y":886},{"x":967,"y":886},{"x":967,"y":937},{"x":860,"y":937}]},"symbols":[{"property":{"detectedLanguages":[{"languageCode":"zh-Hant","confidence":0}],"detectedBreak":null},"boundingBox":{"vertices":[{"x":860,"y":886},{"x":909,"y":886},{"x":909,"y":937},{"x":860,"y":937}]},"text":"更"},{"property":{"detectedLanguages":[{"languageCode":"zh-Hant","confidence":0}],"detectedBreak":null},"boundingBox":{"vertices":[{"x":915,"y":886},{"x":968,"y":886},{"x":968,"y":933},{"x":915,"y":933}]},"text":"新"}]},{"property":{"detectedLanguages":[{"languageCode":"zh-Hant","confidence":0}],"detectedBreak":null},"boundingBox":{"vertices":[{"x":973,"y":884},{"x":1087,"y":884},{"x":1087,"y":933},{"x":973,"y":933}]},"symbols":[{"property":{"detectedLanguages":[{"languageCode":"zh-Hant","confidence":0}],"detectedBreak":null},"boundingBox":{"vertices":[{"x":973,"y":884},{"x":1026,"y":884},{"x":1026,"y":926},{"x":973,"y":926}]},"text":"單"},{"property":{"detectedLanguages":[{"languageCode":"zh-Hant","confidence":0}],"detectedBreak":null},"boundingBox":{"vertices":[{"x":1036,"y":889},{"x":1087,"y":889},{"x":1087,"y":933},{"x":1036,"y":933}]},"text":"元"}]},{"property":{"detectedLanguages":[{"languageCode":"zh-Hant","confidence":0}],"detectedBreak":null},"boundingBox":{"vertices":[{"x":1093,"y":891},{"x":1207,"y":891},{"x":1207,"y":932},{"x":1093,"y":932}]},"symbols":[{"property":{"detectedLanguages":[{"languageCode":"zh-Hant","confidence":0}],"detectedBreak":null},"boundingBox":{"vertices":[{"x":1093,"y":892},{"x":1147,"y":892},{"x":1147,"y":931},{"x":1093,"y":931}]},"text":"位"},{"property":{"detectedLanguages":[{"languageCode":"zh-Hant","confidence":0}],"detectedBreak":null},"boundingBox":{"vertices":[{"x":1150,"y":891},{"x":1208,"y":891},{"x":1208,"y":932},{"x":1150,"y":932}]},"text":"於"}]},{"property":{"detectedLanguages":[{"languageCode":"zh-Hant","confidence":0}],"detectedBreak":null},"boundingBox":{"vertices":[{"x":1213,"y":884},{"x":1379,"y":884},{"x":1379,"y":938},{"x":1213,"y":938}]},"symbols":[{"property":{"detectedLanguages":[{"languageCode":"zh-Hant","confidence":0}],"detectedBreak":null},"boundingBox":{"vertices":[{"x":1213,"y":884},{"x":1262,"y":884},{"x":1262,"y":938},{"x":1213,"y":938}]},"text":"臺"},{"property":{"detectedLanguages":[{"languageCode":"zh-Hant","confidence":0}],"detectedBreak":null},"boundingBox":{"vertices":[{"x":1268,"y":889},{"x":1321,"y":889},{"x":1321,"y":933},{"x":1268,"y":933}]},"text":"北"},{"property":{"detectedLanguages":[{"languageCode":"zh-Hant","confidence":0}],"detectedBreak":null},"boundingBox":{"vertices":[{"x":1328,"y":887},{"x":1379,"y":887},{"x":1379,"y":938},{"x":1328,"y":938}]},"text":"市"}]},{"property":{"detectedLanguages":[{"languageCode":"ja","confidence":0}],"detectedBreak":null},"boundingBox":{"vertices":[{"x":1386,"y":889},{"x":1497,"y":889},{"x":1497,"y":935},{"x":1386,"y":935}]},"symbols":[{"property":{"detectedLanguages":[{"languageCode":"zh-Hant","confidence":0}],"detectedBreak":null},"boundingBox":{"vertices":[{"x":1386,"y":889},{"x":1440,"y":889},{"x":1440,"y":935},{"x":1386,"y":935}]},"text":"大"},{"property":{"detectedLanguages":[{"languageCode":"zh-Hant","confidence":0}],"detectedBreak":null},"boundingBox":{"vertices":[{"x":1444,"y":889},{"x":1497,"y":889},{"x":1497,"y":935},{"x":1444,"y":935}]},"text":"安"}]},{"property":{"detectedLanguages":[{"languageCode":"zh-Hant","confidence":0}],"detectedBreak":null},"boundingBox":{"vertices":[{"x":1508,"y":886},{"x":1552,"y":886},{"x":1552,"y":935},{"x":1508,"y":935}]},"symbols":[{"property":{"detectedLanguages":[{"languageCode":"zh-Hant","confidence":0}],"detectedBreak":null},"boundingBox":{"vertices":[{"x":1508,"y":886},{"x":1552,"y":886},{"x":1552,"y":935},{"x":1508,"y":935}]},"text":"區"}]},{"property":{"detectedLanguages":[{"languageCode":"zh-Hant","confidence":0}],"detectedBreak":null},"boundingBox":{"vertices":[{"x":1563,"y":886},{"x":1667,"y":886},{"x":1667,"y":935},{"x":1563,"y":935}]},"symbols":[{"property":{"detectedLanguages":[{"languageCode":"zh-Hant","confidence":0}],"detectedBreak":null},"boundingBox":{"vertices":[{"x":1563,"y":886},{"x":1617,"y":886},{"x":1617,"y":935},{"x":1563,"y":935}]},"text":"建"},{"property":{"detectedLanguages":[{"languageCode":"zh-Hant","confidence":0}],"detectedBreak":null},"boundingBox":{"vertices":[{"x":1624,"y":889},{"x":1666,"y":889},{"x":1666,"y":933},{"x":1624,"y":933}]},"text":"國"}]},{"property":{"detectedLanguages":[{"languageCode":"zh-Hans","confidence":0}],"detectedBreak":null},"boundingBox":{"vertices":[{"x":1684,"y":884},{"x":1790,"y":884},{"x":1790,"y":935},{"x":1684,"y":935}]},"symbols":[{"property":{"detectedLanguages":[{"languageCode":"zh-Hant","confidence":0}],"detectedBreak":null},"boundingBox":{"vertices":[{"x":1684,"y":884},{"x":1728,"y":884},{"x":1728,"y":935},{"x":1684,"y":935}]},"text":"南"},{"property":{"detectedLanguages":[{"languageCode":"zh-Hant","confidence":0}],"detectedBreak":null},"boundingBox":{"vertices":[{"x":1739,"y":889},{"x":1790,"y":889},{"x":1790,"y":933},{"x":1739,"y":933}]},"text":"路"}]},{"property":{"detectedLanguages":[{"languageCode":"zh-Hans","confidence":0}],"detectedBreak":null},"boundingBox":{"vertices":[{"x":1796,"y":887},{"x":1910,"y":887},{"x":1910,"y":934},{"x":1796,"y":934}]},"symbols":[{"property":{"detectedLanguages":[{"languageCode":"zh-Hant","confidence":0}],"detectedBreak":null},"boundingBox":{"vertices":[{"x":1796,"y":894},{"x":1850,"y":894},{"x":1850,"y":928},{"x":1796,"y":928}]},"text":"二"},{"property":{"detectedLanguages":[{"languageCode":"zh-Hant","confidence":0}],"detectedBreak":null},"boundingBox":{"vertices":[{"x":1852,"y":887},{"x":1910,"y":887},{"x":1910,"y":934},{"x":1852,"y":934}]},"text":"段"}]},{"property":{"detectedLanguages":[{"languageCode":"en","confidence":0}],"detectedBreak":null},"boundingBox":{"vertices":[{"x":1926,"y":886},{"x":1982,"y":886},{"x":1982,"y":930},{"x":1926,"y":930}]},"symbols":[{"property":{"detectedLanguages":[{"languageCode":"zh-Hant","confidence":0}],"detectedBreak":null},"boundingBox":{"vertices":[{"x":1926,"y":886},{"x":1953,"y":886},{"x":1953,"y":930},{"x":1926,"y":930}]},"text":"6"},{"property":{"detectedLanguages":[{"languageCode":"zh-Hant","confidence":0}],"detectedBreak":null},"boundingBox":{"vertices":[{"x":1955,"y":886},{"x":1982,"y":886},{"x":1982,"y":930},{"x":1955,"y":930}]},"text":"9"}]},{"property":{"detectedLanguages":[{"languageCode":"zh-Hans","confidence":0}],"detectedBreak":null},"boundingBox":{"vertices":[{"x":2001,"y":886},{"x":2055,"y":886},{"x":2055,"y":935},{"x":2001,"y":935}]},"symbols":[{"property":{"detectedLanguages":[{"languageCode":"zh-Hant","confidence":0}],"detectedBreak":null},"boundingBox":{"vertices":[{"x":2001,"y":886},{"x":2055,"y":886},{"x":2055,"y":935},{"x":2001,"y":935}]},"text":"巷"}]},{"property":{"detectedLanguages":[{"languageCode":"en","confidence":0}],"detectedBreak":null},"boundingBox":{"vertices":[{"x":2080,"y":901},{"x":2090,"y":901},{"x":2090,"y":918},{"x":2080,"y":918}]},"symbols":[{"property":{"detectedLanguages":[{"languageCode":"zh-Hant","confidence":0}],"detectedBreak":{"type":"EOL_SURE_SPACE","isPrefix":false}},"boundingBox":{"vertices":[{"x":2080,"y":901},{"x":2090,"y":901},{"x":2090,"y":918},{"x":2080,"y":918}]},"text":","}]}]}],"blockType":"TEXT"},{"property":{"detectedLanguages":[{"languageCode":"zh-Hant","confidence":0}],"detectedBreak":null},"boundingBox":{"vertices":[{"x":807,"y":1035},{"x":2095,"y":1035},{"x":2095,"y":1089},{"x":807,"y":1089}]},"paragraphs":[{"property":{"detectedLanguages":[{"languageCode":"zh-Hant","confidence":0}],"detectedBreak":null},"boundingBox":{"vertices":[{"x":807,"y":1035},{"x":2095,"y":1035},{"x":2095,"y":1089},{"x":807,"y":1089}]},"words":[{"property":{"detectedLanguages":[{"languageCode":"zh-Hant","confidence":0}],"detectedBreak":null},"boundingBox":{"vertices":[{"x":807,"y":1035},{"x":916,"y":1035},{"x":916,"y":1089},{"x":807,"y":1089}]},"symbols":[{"property":{"detectedLanguages":[{"languageCode":"zh-Hant","confidence":0}],"detectedBreak":null},"boundingBox":{"vertices":[{"x":807,"y":1040},{"x":858,"y":1040},{"x":858,"y":1086},{"x":807,"y":1086}]},"text":"信"},{"property":{"detectedLanguages":[{"languageCode":"zh-Hant","confidence":0}],"detectedBreak":null},"boundingBox":{"vertices":[{"x":870,"y":1035},{"x":916,"y":1035},{"x":916,"y":1089},{"x":870,"y":1089}]},"text":"義"}]},{"property":{"detectedLanguages":[{"languageCode":"zh-Hans","confidence":0}],"detectedBreak":null},"boundingBox":{"vertices":[{"x":923,"y":1040},{"x":1097,"y":1040},{"x":1097,"y":1086},{"x":923,"y":1086}]},"symbols":[{"property":{"detectedLanguages":[{"languageCode":"zh-Hant","confidence":0}],"detectedBreak":null},"boundingBox":{"vertices":[{"x":923,"y":1040},{"x":977,"y":1040},{"x":977,"y":1086},{"x":923,"y":1086}]},"text":"路"},{"property":{"detectedLanguages":[{"languageCode":"zh-Hant","confidence":0}],"detectedBreak":null},"boundingBox":{"vertices":[{"x":983,"y":1043},{"x":1037,"y":1043},{"x":1037,"y":1084},{"x":983,"y":1084}]},"text":"三"},{"property":{"detectedLanguages":[{"languageCode":"zh-Hant","confidence":0}],"detectedBreak":null},"boundingBox":{"vertices":[{"x":1043,"y":1040},{"x":1097,"y":1040},{"x":1097,"y":1086},{"x":1043,"y":1086}]},"text":"段"}]},{"property":{"detectedLanguages":[{"languageCode":"en","confidence":0}],"detectedBreak":null},"boundingBox":{"vertices":[{"x":1120,"y":1038},{"x":1202,"y":1038},{"x":1202,"y":1084},{"x":1120,"y":1084}]},"symbols":[{"property":{"detectedLanguages":[{"languageCode":"zh-Hant","confidence":0}],"detectedBreak":null},"boundingBox":{"vertices":[{"x":1120,"y":1038},{"x":1143,"y":1038},{"x":1143,"y":1084},{"x":1120,"y":1084}]},"text":"1"},{"property":{"detectedLanguages":[{"languageCode":"zh-Hant","confidence":0}],"detectedBreak":null},"boundingBox":{"vertices":[{"x":1146,"y":1038},{"x":1171,"y":1038},{"x":1171,"y":1084},{"x":1146,"y":1084}]},"text":"3"},{"property":{"detectedLanguages":[{"languageCode":"zh-Hant","confidence":0}],"detectedBreak":null},"boundingBox":{"vertices":[{"x":1175,"y":1038},{"x":1202,"y":1038},{"x":1202,"y":1082},{"x":1175,"y":1082}]},"text":"4"}]},{"property":{"detectedLanguages":[{"languageCode":"zh-Hans","confidence":0}],"detectedBreak":null},"boundingBox":{"vertices":[{"x":1221,"y":1036},{"x":1272,"y":1036},{"x":1272,"y":1089},{"x":1221,"y":1089}]},"symbols":[{"property":{"detectedLanguages":[{"languageCode":"zh-Hant","confidence":0}],"detectedBreak":null},"boundingBox":{"vertices":[{"x":1221,"y":1036},{"x":1272,"y":1036},{"x":1272,"y":1089},{"x":1221,"y":1089}]},"text":"巷"}]},{"property":{"detectedLanguages":[{"languageCode":"zh-Hans","confidence":0}],"detectedBreak":null},"boundingBox":{"vertices":[{"x":1280,"y":1040},{"x":1333,"y":1040},{"x":1333,"y":1084},{"x":1280,"y":1084}]},"symbols":[{"property":{"detectedLanguages":[{"languageCode":"zh-Hant","confidence":0}],"detectedBreak":null},"boundingBox":{"vertices":[{"x":1280,"y":1040},{"x":1333,"y":1040},{"x":1333,"y":1084},{"x":1280,"y":1084}]},"text":"及"}]},{"property":{"detectedLanguages":[{"languageCode":"zh-Hant","confidence":0}],"detectedBreak":null},"boundingBox":{"vertices":[{"x":1338,"y":1038},{"x":1444,"y":1038},{"x":1444,"y":1089},{"x":1338,"y":1089}]},"symbols":[{"property":{"detectedLanguages":[{"languageCode":"zh-Hant","confidence":0}],"detectedBreak":null},"boundingBox":{"vertices":[{"x":1338,"y":1038},{"x":1391,"y":1038},{"x":1391,"y":1089},{"x":1338,"y":1089}]},"text":"建"},{"property":{"detectedLanguages":[{"languageCode":"zh-Hant","confidence":0}],"detectedBreak":null},"boundingBox":{"vertices":[{"x":1400,"y":1040},{"x":1444,"y":1040},{"x":1444,"y":1086},{"x":1400,"y":1086}]},"text":"國"}]},{"property":{"detectedLanguages":[{"languageCode":"zh-Hans","confidence":0}],"detectedBreak":null},"boundingBox":{"vertices":[{"x":1461,"y":1036},{"x":1567,"y":1036},{"x":1567,"y":1087},{"x":1461,"y":1087}]},"symbols":[{"property":{"detectedLanguages":[{"languageCode":"zh-Hant","confidence":0}],"detectedBreak":null},"boundingBox":{"vertices":[{"x":1461,"y":1036},{"x":1505,"y":1036},{"x":1505,"y":1087},{"x":1461,"y":1087}]},"text":"南"},{"property":{"detectedLanguages":[{"languageCode":"zh-Hant","confidence":0}],"detectedBreak":null},"boundingBox":{"vertices":[{"x":1515,"y":1040},{"x":1568,"y":1040},{"x":1568,"y":1084},{"x":1515,"y":1084}]},"text":"路"}]},{"property":{"detectedLanguages":[{"languageCode":"zh-Hans","confidence":0}],"detectedBreak":null},"boundingBox":{"vertices":[{"x":1571,"y":1038},{"x":1685,"y":1038},{"x":1685,"y":1085},{"x":1571,"y":1085}]},"symbols":[{"property":{"detectedLanguages":[{"languageCode":"zh-Hant","confidence":0}],"detectedBreak":null},"boundingBox":{"vertices":[{"x":1571,"y":1047},{"x":1625,"y":1047},{"x":1625,"y":1079},{"x":1571,"y":1079}]},"text":"二"},{"property":{"detectedLanguages":[{"languageCode":"zh-Hant","confidence":0}],"detectedBreak":null},"boundingBox":{"vertices":[{"x":1629,"y":1038},{"x":1685,"y":1038},{"x":1685,"y":1085},{"x":1629,"y":1085}]},"text":"段"}]},{"property":{"detectedLanguages":[{"languageCode":"zh-Hans","confidence":0}],"detectedBreak":null},"boundingBox":{"vertices":[{"x":1688,"y":1040},{"x":1741,"y":1040},{"x":1741,"y":1084},{"x":1688,"y":1084}]},"symbols":[{"property":{"detectedLanguages":[{"languageCode":"zh-Hant","confidence":0}],"detectedBreak":null},"boundingBox":{"vertices":[{"x":1688,"y":1040},{"x":1741,"y":1040},{"x":1741,"y":1084},{"x":1688,"y":1084}]},"text":"所"}]},{"property":{"detectedLanguages":[{"languageCode":"zh-Hant","confidence":0}],"detectedBreak":null},"boundingBox":{"vertices":[{"x":1751,"y":1036},{"x":1797,"y":1036},{"x":1797,"y":1087},{"x":1751,"y":1087}]},"symbols":[{"property":{"detectedLanguages":[{"languageCode":"zh-Hant","confidence":0}],"detectedBreak":null},"boundingBox":{"vertices":[{"x":1751,"y":1036},{"x":1797,"y":1036},{"x":1797,"y":1087},{"x":1751,"y":1087}]},"text":"圍"}]},{"property":{"detectedLanguages":[{"languageCode":"zh-Hans","confidence":0}],"detectedBreak":null},"boundingBox":{"vertices":[{"x":1808,"y":1036},{"x":1917,"y":1036},{"x":1917,"y":1089},{"x":1808,"y":1089}]},"symbols":[{"property":{"detectedLanguages":[{"languageCode":"zh-Hant","confidence":0}],"detectedBreak":null},"boundingBox":{"vertices":[{"x":1808,"y":1040},{"x":1861,"y":1040},{"x":1861,"y":1089},{"x":1808,"y":1089}]},"text":"街"},{"property":{"detectedLanguages":[{"languageCode":"zh-Hant","confidence":0}],"detectedBreak":null},"boundingBox":{"vertices":[{"x":1866,"y":1036},{"x":1917,"y":1036},{"x":1917,"y":1089},{"x":1866,"y":1089}]},"text":"廓"}]},{"property":{"detectedLanguages":[{"languageCode":"zh-Hant","confidence":0}],"detectedBreak":null},"boundingBox":{"vertices":[{"x":1929,"y":1042},{"x":1971,"y":1042},{"x":1971,"y":1086},{"x":1929,"y":1086}]},"symbols":[{"property":{"detectedLanguages":[{"languageCode":"zh-Hant","confidence":0}],"detectedBreak":null},"boundingBox":{"vertices":[{"x":1929,"y":1042},{"x":1971,"y":1042},{"x":1971,"y":1086},{"x":1929,"y":1086}]},"text":"內"}]},{"property":{"detectedLanguages":[{"languageCode":"zh-Hans","confidence":0}],"detectedBreak":null},"boundingBox":{"vertices":[{"x":1982,"y":1045},{"x":2036,"y":1045},{"x":2036,"y":1084},{"x":1982,"y":1084}]},"symbols":[{"property":{"detectedLanguages":[{"languageCode":"zh-Hant","confidence":0}],"detectedBreak":null},"boundingBox":{"vertices":[{"x":1982,"y":1045},{"x":2036,"y":1045},{"x":2036,"y":1084},{"x":1982,"y":1084}]},"text":"之"}]},{"property":{"detectedLanguages":[{"languageCode":"ja","confidence":0}],"detectedBreak":null},"boundingBox":{"vertices":[{"x":2044,"y":1036},{"x":2095,"y":1036},{"x":2095,"y":1089},{"x":2044,"y":1089}]},"symbols":[{"property":{"detectedLanguages":[{"languageCode":"zh-Hant","confidence":0}],"detectedBreak":{"type":"EOL_SURE_SPACE","isPrefix":false}},"boundingBox":{"vertices":[{"x":2044,"y":1036},{"x":2095,"y":1036},{"x":2095,"y":1089},{"x":2044,"y":1089}]},"text":"東"}]}]}],"blockType":"TEXT"},{"property":{"detectedLanguages":[{"languageCode":"zh-Hant","confidence":0}],"detectedBreak":null},"boundingBox":{"vertices":[{"x":411,"y":1336},{"x":2100,"y":1336},{"x":2100,"y":1390},{"x":411,"y":1390}]},"paragraphs":[{"property":{"detectedLanguages":[{"languageCode":"zh-Hant","confidence":0}],"detectedBreak":null},"boundingBox":{"vertices":[{"x":411,"y":1336},{"x":2100,"y":1336},{"x":2100,"y":1390},{"x":411,"y":1390}]},"words":[{"property":{"detectedLanguages":[{"languageCode":"zh-Hans","confidence":0}],"detectedBreak":null},"boundingBox":{"vertices":[{"x":411,"y":1348},{"x":465,"y":1348},{"x":465,"y":1380},{"x":411,"y":1380}]},"symbols":[{"property":{"detectedLanguages":[{"languageCode":"zh-Hant","confidence":0}],"detectedBreak":null},"boundingBox":{"vertices":[{"x":411,"y":1348},{"x":465,"y":1348},{"x":465,"y":1380},{"x":411,"y":1380}]},"text":"二"}]},{"property":{"detectedLanguages":[{"languageCode":"en","confidence":0}],"detectedBreak":null},"boundingBox":{"vertices":[{"x":488,"y":1355},{"x":505,"y":1355},{"x":505,"y":1370},{"x":488,"y":1370}]},"symbols":[{"property":{"detectedLanguages":[{"languageCode":"zh-Hant","confidence":0}],"detectedBreak":null},"boundingBox":{"vertices":[{"x":488,"y":1355},{"x":505,"y":1355},{"x":505,"y":1370},{"x":488,"y":1370}]},"text":"、"}]},{"property":{"detectedLanguages":[{"languageCode":"zh-Hant","confidence":0}],"detectedBreak":null},"boundingBox":{"vertices":[{"x":529,"y":1340},{"x":636,"y":1340},{"x":636,"y":1391},{"x":529,"y":1391}]},"symbols":[{"property":{"detectedLanguages":[{"languageCode":"zh-Hant","confidence":0}],"detectedBreak":null},"boundingBox":{"vertices":[{"x":529,"y":1340},{"x":580,"y":1340},{"x":580,"y":1391},{"x":529,"y":1391}]},"text":"計"},{"property":{"detectedLanguages":[{"languageCode":"zh-Hant","confidence":0}],"detectedBreak":null},"boundingBox":{"vertices":[{"x":591,"y":1340},{"x":637,"y":1340},{"x":637,"y":1391},{"x":591,"y":1391}]},"text":"畫"}]},{"property":{"detectedLanguages":[{"languageCode":"zh-Hant","confidence":0}],"detectedBreak":null},"boundingBox":{"vertices":[{"x":646,"y":1336},{"x":753,"y":1336},{"x":753,"y":1389},{"x":646,"y":1389}]},"symbols":[{"property":{"detectedLanguages":[{"languageCode":"zh-Hant","confidence":0}],"detectedBreak":null},"boundingBox":{"vertices":[{"x":646,"y":1336},{"x":697,"y":1336},{"x":697,"y":1389},{"x":646,"y":1389}]},"text":"範"},{"property":{"detectedLanguages":[{"languageCode":"zh-Hant","confidence":0}],"detectedBreak":null},"boundingBox":{"vertices":[{"x":707,"y":1338},{"x":753,"y":1338},{"x":753,"y":1389},{"x":707,"y":1389}]},"text":"圍"}]},{"property":{"detectedLanguages":[{"languageCode":"en","confidence":0}],"detectedBreak":null},"boundingBox":{"vertices":[{"x":783,"y":1343},{"x":796,"y":1343},{"x":796,"y":1375},{"x":783,"y":1375}]},"symbols":[{"property":{"detectedLanguages":[{"languageCode":"zh-Hant","confidence":0}],"detectedBreak":null},"boundingBox":{"vertices":[{"x":783,"y":1343},{"x":796,"y":1343},{"x":796,"y":1375},{"x":783,"y":1375}]},"text":":"}]},{"property":{"detectedLanguages":[{"languageCode":"zh-Hant","confidence":0}],"detectedBreak":null},"boundingBox":{"vertices":[{"x":826,"y":1336},{"x":990,"y":1336},{"x":990,"y":1390},{"x":826,"y":1390}]},"symbols":[{"property":{"detectedLanguages":[{"languageCode":"zh-Hant","confidence":0}],"detectedBreak":null},"boundingBox":{"vertices":[{"x":826,"y":1336},{"x":873,"y":1336},{"x":873,"y":1390},{"x":826,"y":1390}]},"text":"臺"},{"property":{"detectedLanguages":[{"languageCode":"zh-Hant","confidence":0}],"detectedBreak":null},"boundingBox":{"vertices":[{"x":882,"y":1341},{"x":933,"y":1341},{"x":933,"y":1385},{"x":882,"y":1385}]},"text":"北"},{"property":{"detectedLanguages":[{"languageCode":"zh-Hant","confidence":0}],"detectedBreak":null},"boundingBox":{"vertices":[{"x":940,"y":1340},{"x":989,"y":1340},{"x":989,"y":1391},{"x":940,"y":1391}]},"text":"市"}]},{"property":{"detectedLanguages":[{"languageCode":"ja","confidence":0}],"detectedBreak":null},"boundingBox":{"vertices":[{"x":1000,"y":1341},{"x":1109,"y":1341},{"x":1109,"y":1388},{"x":1000,"y":1388}]},"symbols":[{"property":{"detectedLanguages":[{"languageCode":"zh-Hant","confidence":0}],"detectedBreak":null},"boundingBox":{"vertices":[{"x":1000,"y":1341},{"x":1053,"y":1341},{"x":1053,"y":1387},{"x":1000,"y":1387}]},"text":"大"},{"property":{"detectedLanguages":[{"languageCode":"zh-Hant","confidence":0}],"detectedBreak":null},"boundingBox":{"vertices":[{"x":1057,"y":1341},{"x":1110,"y":1341},{"x":1110,"y":1388},{"x":1057,"y":1388}]},"text":"安"}]},{"property":{"detectedLanguages":[{"languageCode":"zh-Hant","confidence":0}],"detectedBreak":null},"boundingBox":{"vertices":[{"x":1120,"y":1340},{"x":1167,"y":1340},{"x":1167,"y":1387},{"x":1120,"y":1387}]},"symbols":[{"property":{"detectedLanguages":[{"languageCode":"zh-Hant","confidence":0}],"detectedBreak":null},"boundingBox":{"vertices":[{"x":1120,"y":1340},{"x":1167,"y":1340},{"x":1167,"y":1387},{"x":1120,"y":1387}]},"text":"區"}]},{"property":{"detectedLanguages":[{"languageCode":"zh-Hans","confidence":0}],"detectedBreak":null},"boundingBox":{"vertices":[{"x":1177,"y":1340},{"x":1286,"y":1340},{"x":1286,"y":1389},{"x":1177,"y":1389}]},"symbols":[{"property":{"detectedLanguages":[{"languageCode":"zh-Hant","confidence":0}],"detectedBreak":null},"boundingBox":{"vertices":[{"x":1177,"y":1340},{"x":1230,"y":1340},{"x":1230,"y":1389},{"x":1177,"y":1389}]},"text":"瑞"},{"property":{"detectedLanguages":[{"languageCode":"zh-Hant","confidence":0}],"detectedBreak":null},"boundingBox":{"vertices":[{"x":1235,"y":1340},{"x":1286,"y":1340},{"x":1286,"y":1387},{"x":1235,"y":1387}]},"text":"安"}]},{"property":{"detectedLanguages":[{"languageCode":"zh-Hans","confidence":0}],"detectedBreak":null},"boundingBox":{"vertices":[{"x":1292,"y":1340},{"x":1350,"y":1340},{"x":1350,"y":1387},{"x":1292,"y":1387}]},"symbols":[{"property":{"detectedLanguages":[{"languageCode":"zh-Hant","confidence":0}],"detectedBreak":null},"boundingBox":{"vertices":[{"x":1292,"y":1340},{"x":1350,"y":1340},{"x":1350,"y":1387},{"x":1292,"y":1387}]},"text":"段"}]},{"property":{"detectedLanguages":[{"languageCode":"zh-Hans","confidence":0}],"detectedBreak":null},"boundingBox":{"vertices":[{"x":1355,"y":1340},{"x":1524,"y":1340},{"x":1524,"y":1389},{"x":1355,"y":1389}]},"symbols":[{"property":{"detectedLanguages":[{"languageCode":"zh-Hant","confidence":0}],"detectedBreak":null},"boundingBox":{"vertices":[{"x":1355,"y":1359},{"x":1401,"y":1359},{"x":1401,"y":1369},{"x":1355,"y":1369}]},"text":"一"},{"property":{"detectedLanguages":[{"languageCode":"zh-Hant","confidence":0}],"detectedBreak":null},"boundingBox":{"vertices":[{"x":1413,"y":1341},{"x":1460,"y":1341},{"x":1460,"y":1388},{"x":1413,"y":1388}]},"text":"小"},{"property":{"detectedLanguages":[{"languageCode":"zh-Hant","confidence":0}],"detectedBreak":null},"boundingBox":{"vertices":[{"x":1468,"y":1340},{"x":1524,"y":1340},{"x":1524,"y":1387},{"x":1468,"y":1387}]},"text":"段"}]},{"property":{"detectedLanguages":[{"languageCode":"en","confidence":0}],"detectedBreak":null},"boundingBox":{"vertices":[{"x":1540,"y":1338},{"x":1671,"y":1338},{"x":1671,"y":1384},{"x":1540,"y":1384}]},"symbols":[{"property":{"detectedLanguages":[{"languageCode":"zh-Hant","confidence":0}],"detectedBreak":null},"boundingBox":{"vertices":[{"x":1540,"y":1338},{"x":1567,"y":1338},{"x":1567,"y":1382},{"x":1540,"y":1382}]},"text":"2"},{"property":{"detectedLanguages":[{"languageCode":"zh-Hant","confidence":0}],"detectedBreak":null},"boundingBox":{"vertices":[{"x":1568,"y":1338},{"x":1593,"y":1338},{"x":1593,"y":1382},{"x":1568,"y":1382}]},"text":"2"},{"property":{"detectedLanguages":[{"languageCode":"zh-Hant","confidence":0}],"detectedBreak":null},"boundingBox":{"vertices":[{"x":1595,"y":1338},{"x":1618,"y":1338},{"x":1618,"y":1382},{"x":1595,"y":1382}]},"text":"1"},{"property":{"detectedLanguages":[{"languageCode":"zh-Hant","confidence":0}],"detectedBreak":null},"boundingBox":{"vertices":[{"x":1628,"y":1338},{"x":1648,"y":1338},{"x":1648,"y":1384},{"x":1628,"y":1384}]},"text":"-"},{"property":{"detectedLanguages":[{"languageCode":"zh-Hant","confidence":0}],"detectedBreak":{"type":"SPACE","isPrefix":false}},"boundingBox":{"vertices":[{"x":1650,"y":1338},{"x":1672,"y":1338},{"x":1672,"y":1384},{"x":1650,"y":1384}]},"text":"3"}]},{"property":{"detectedLanguages":[{"languageCode":"en","confidence":0}],"detectedBreak":null},"boundingBox":{"vertices":[{"x":1696,"y":1357},{"x":1713,"y":1357},{"x":1713,"y":1370},{"x":1696,"y":1370}]},"symbols":[{"property":{"detectedLanguages":[{"languageCode":"zh-Hant","confidence":0}],"detectedBreak":{"type":"SPACE","isPrefix":false}},"boundingBox":{"vertices":[{"x":1696,"y":1357},{"x":1713,"y":1357},{"x":1713,"y":1370},{"x":1696,"y":1370}]},"text":","}]},{"property":{"detectedLanguages":[{"languageCode":"en","confidence":0}],"detectedBreak":null},"boundingBox":{"vertices":[{"x":1734,"y":1338},{"x":1970,"y":1338},{"x":1970,"y":1382},{"x":1734,"y":1382}]},"symbols":[{"property":{"detectedLanguages":[{"languageCode":"zh-Hant","confidence":0}],"detectedBreak":null},"boundingBox":{"vertices":[{"x":1734,"y":1338},{"x":1764,"y":1338},{"x":1764,"y":1382},{"x":1734,"y":1382}]},"text":"2"},{"property":{"detectedLanguages":[{"languageCode":"zh-Hant","confidence":0}],"detectedBreak":null},"boundingBox":{"vertices":[{"x":1765,"y":1338},{"x":1792,"y":1338},{"x":1792,"y":1382},{"x":1765,"y":1382}]},"text":"2"},{"property":{"detectedLanguages":[{"languageCode":"zh-Hant","confidence":0}],"detectedBreak":null},"boundingBox":{"vertices":[{"x":1794,"y":1338},{"x":1819,"y":1338},{"x":1819,"y":1382},{"x":1794,"y":1382}]},"text":"5"},{"property":{"detectedLanguages":[{"languageCode":"zh-Hant","confidence":0}],"detectedBreak":null},"boundingBox":{"vertices":[{"x":1844,"y":1357},{"x":1861,"y":1357},{"x":1861,"y":1370},{"x":1844,"y":1370}]},"text":"、"},{"property":{"detectedLanguages":[{"languageCode":"zh-Hant","confidence":0}],"detectedBreak":null},"boundingBox":{"vertices":[{"x":1881,"y":1338},{"x":1910,"y":1338},{"x":1910,"y":1382},{"x":1881,"y":1382}]},"text":"2"},{"property":{"detectedLanguages":[{"languageCode":"zh-Hant","confidence":0}],"detectedBreak":null},"boundingBox":{"vertices":[{"x":1910,"y":1338},{"x":1937,"y":1338},{"x":1937,"y":1382},{"x":1910,"y":1382}]},"text":"2"},{"property":{"detectedLanguages":[{"languageCode":"zh-Hant","confidence":0}],"detectedBreak":null},"boundingBox":{"vertices":[{"x":1941,"y":1338},{"x":1970,"y":1338},{"x":1970,"y":1382},{"x":1941,"y":1382}]},"text":"6"}]},{"property":{"detectedLanguages":[{"languageCode":"ja","confidence":0}],"detectedBreak":null},"boundingBox":{"vertices":[{"x":1986,"y":1340},{"x":2042,"y":1340},{"x":2042,"y":1386},{"x":1986,"y":1386}]},"symbols":[{"property":{"detectedLanguages":[{"languageCode":"zh-Hant","confidence":0}],"detectedBreak":null},"boundingBox":{"vertices":[{"x":1986,"y":1340},{"x":2042,"y":1340},{"x":2042,"y":1386},{"x":1986,"y":1386}]},"text":"地"}]},{"property":{"detectedLanguages":[{"languageCode":"zh-Hant","confidence":0}],"detectedBreak":null},"boundingBox":{"vertices":[{"x":2048,"y":1340},{"x":2101,"y":1340},{"x":2101,"y":1389},{"x":2048,"y":1389}]},"symbols":[{"property":{"detectedLanguages":[{"languageCode":"zh-Hant","confidence":0}],"detectedBreak":{"type":"EOL_SURE_SPACE","isPrefix":false}},"boundingBox":{"vertices":[{"x":2048,"y":1340},{"x":2101,"y":1340},{"x":2101,"y":1389},{"x":2048,"y":1389}]},"text":"號"}]}]}],"blockType":"TEXT"},{"property":{"detectedLanguages":[{"languageCode":"zh-Hant","confidence":0}],"detectedBreak":null},"boundingBox":{"vertices":[{"x":807,"y":1487},{"x":1129,"y":1491},{"x":1128,"y":1544},{"x":806,"y":1540}]},"paragraphs":[{"property":{"detectedLanguages":[{"languageCode":"zh-Hant","confidence":0}],"detectedBreak":null},"boundingBox":{"vertices":[{"x":807,"y":1487},{"x":1130,"y":1487},{"x":1130,"y":1541},{"x":807,"y":1541}]},"words":[{"property":{"detectedLanguages":[{"languageCode":"ja","confidence":0}],"detectedBreak":null},"boundingBox":{"vertices":[{"x":807,"y":1487},{"x":855,"y":1488},{"x":854,"y":1541},{"x":806,"y":1540}]},"symbols":[{"property":{"detectedLanguages":[{"languageCode":"zh-Hant","confidence":0}],"detectedBreak":null},"boundingBox":{"vertices":[{"x":807,"y":1487},{"x":855,"y":1488},{"x":854,"y":1541},{"x":806,"y":1540}]},"text":"等"}]},{"property":{"detectedLanguages":[{"languageCode":"en","confidence":0}],"detectedBreak":null},"boundingBox":{"vertices":[{"x":874,"y":1489},{"x":896,"y":1489},{"x":895,"y":1534},{"x":873,"y":1534}]},"symbols":[{"property":{"detectedLanguages":[{"languageCode":"zh-Hant","confidence":0}],"detectedBreak":null},"boundingBox":{"vertices":[{"x":874,"y":1489},{"x":896,"y":1489},{"x":895,"y":1534},{"x":873,"y":1534}]},"text":"3"}]},{"property":{"detectedLanguages":[{"languageCode":"zh-Hant","confidence":0}],"detectedBreak":null},"boundingBox":{"vertices":[{"x":923,"y":1489},{"x":969,"y":1490},{"x":968,"y":1538},{"x":922,"y":1537}]},"symbols":[{"property":{"detectedLanguages":[{"languageCode":"zh-Hant","confidence":0}],"detectedBreak":null},"boundingBox":{"vertices":[{"x":923,"y":1489},{"x":969,"y":1490},{"x":968,"y":1538},{"x":922,"y":1537}]},"text":"筆"}]},{"property":{"detectedLanguages":[{"languageCode":"ja","confidence":0}],"detectedBreak":null},"boundingBox":{"vertices":[{"x":980,"y":1491},{"x":1092,"y":1492},{"x":1091,"y":1537},{"x":979,"y":1536}]},"symbols":[{"property":{"detectedLanguages":[{"languageCode":"zh-Hant","confidence":0}],"detectedBreak":null},"boundingBox":{"vertices":[{"x":980,"y":1491},{"x":1028,"y":1492},{"x":1027,"y":1535},{"x":979,"y":1534}]},"text":"土"},{"property":{"detectedLanguages":[{"languageCode":"zh-Hant","confidence":0}],"detectedBreak":null},"boundingBox":{"vertices":[{"x":1038,"y":1492},{"x":1091,"y":1493},{"x":1090,"y":1538},{"x":1037,"y":1537}]},"text":"地"}]},{"property":{"detectedLanguages":[{"languageCode":"en","confidence":0}],"detectedBreak":null},"boundingBox":{"vertices":[{"x":1115,"y":1506},{"x":1129,"y":1506},{"x":1129,"y":1520},{"x":1115,"y":1520}]},"symbols":[{"property":{"detectedLanguages":[{"languageCode":"zh-Hant","confidence":0}],"detectedBreak":{"type":"EOL_SURE_SPACE","isPrefix":false}},"boundingBox":{"vertices":[{"x":1115,"y":1506},{"x":1129,"y":1506},{"x":1129,"y":1520},{"x":1115,"y":1520}]},"text":"。"}]}]}],"blockType":"TEXT"},{"property":{"detectedLanguages":[{"languageCode":"zh-Hant","confidence":0}],"detectedBreak":null},"boundingBox":{"vertices":[{"x":411,"y":1638},{"x":1240,"y":1638},{"x":1240,"y":1692},{"x":411,"y":1692}]},"paragraphs":[{"property":{"detectedLanguages":[{"languageCode":"zh-Hant","confidence":0}],"detectedBreak":null},"boundingBox":{"vertices":[{"x":411,"y":1638},{"x":1240,"y":1638},{"x":1240,"y":1692},{"x":411,"y":1692}]},"words":[{"property":{"detectedLanguages":[{"languageCode":"zh-Hans","confidence":0}],"detectedBreak":null},"boundingBox":{"vertices":[{"x":411,"y":1645},{"x":465,"y":1645},{"x":465,"y":1686},{"x":411,"y":1686}]},"symbols":[{"property":{"detectedLanguages":[{"languageCode":"zh-Hant","confidence":0}],"detectedBreak":null},"boundingBox":{"vertices":[{"x":411,"y":1645},{"x":465,"y":1645},{"x":465,"y":1686},{"x":411,"y":1686}]},"text":"三"}]},{"property":{"detectedLanguages":[{"languageCode":"en","confidence":0}],"detectedBreak":null},"boundingBox":{"vertices":[{"x":490,"y":1657},{"x":507,"y":1657},{"x":507,"y":1672},{"x":490,"y":1672}]},"symbols":[{"property":{"detectedLanguages":[{"languageCode":"zh-Hant","confidence":0}],"detectedBreak":null},"boundingBox":{"vertices":[{"x":490,"y":1657},{"x":507,"y":1657},{"x":507,"y":1672},{"x":490,"y":1672}]},"text":"、"}]},{"property":{"detectedLanguages":[{"languageCode":"zh-Hant","confidence":0}],"detectedBreak":null},"boundingBox":{"vertices":[{"x":527,"y":1638},{"x":638,"y":1638},{"x":638,"y":1692},{"x":527,"y":1692}]},"symbols":[{"property":{"detectedLanguages":[{"languageCode":"zh-Hant","confidence":0}],"detectedBreak":null},"boundingBox":{"vertices":[{"x":527,"y":1640},{"x":581,"y":1640},{"x":581,"y":1687},{"x":527,"y":1687}]},"text":"計"},{"property":{"detectedLanguages":[{"languageCode":"zh-Hant","confidence":0}],"detectedBreak":null},"boundingBox":{"vertices":[{"x":591,"y":1638},{"x":638,"y":1638},{"x":638,"y":1692},{"x":591,"y":1692}]},"text":"畫"}]},{"property":{"detectedLanguages":[{"languageCode":"zh-Hant","confidence":0}],"detectedBreak":null},"boundingBox":{"vertices":[{"x":649,"y":1641},{"x":756,"y":1641},{"x":756,"y":1690},{"x":649,"y":1690}]},"symbols":[{"property":{"detectedLanguages":[{"languageCode":"zh-Hant","confidence":0}],"detectedBreak":null},"boundingBox":{"vertices":[{"x":649,"y":1643},{"x":693,"y":1643},{"x":693,"y":1685},{"x":649,"y":1685}]},"text":"面"},{"property":{"detectedLanguages":[{"languageCode":"zh-Hant","confidence":0}],"detectedBreak":null},"boundingBox":{"vertices":[{"x":702,"y":1641},{"x":756,"y":1641},{"x":756,"y":1690},{"x":702,"y":1690}]},"text":"積"}]},{"property":{"detectedLanguages":[{"languageCode":"en","confidence":0}],"detectedBreak":null},"boundingBox":{"vertices":[{"x":784,"y":1645},{"x":795,"y":1645},{"x":795,"y":1677},{"x":784,"y":1677}]},"symbols":[{"property":{"detectedLanguages":[{"languageCode":"zh-Hant","confidence":0}],"detectedBreak":{"type":"SPACE","isPrefix":false}},"boundingBox":{"vertices":[{"x":784,"y":1645},{"x":795,"y":1645},{"x":795,"y":1677},{"x":784,"y":1677}]},"text":":"}]},{"property":{"detectedLanguages":[{"languageCode":"en","confidence":0}],"detectedBreak":null},"boundingBox":{"vertices":[{"x":826,"y":1640},{"x":949,"y":1640},{"x":949,"y":1693},{"x":826,"y":1693}]},"symbols":[{"property":{"detectedLanguages":[{"languageCode":"zh-Hant","confidence":0}],"detectedBreak":null},"boundingBox":{"vertices":[{"x":826,"y":1641},{"x":843,"y":1641},{"x":843,"y":1683},{"x":826,"y":1683}]},"text":"1"},{"property":{"detectedLanguages":[{"languageCode":"zh-Hant","confidence":0}],"detectedBreak":null},"boundingBox":{"vertices":[{"x":851,"y":1674},{"x":862,"y":1674},{"x":862,"y":1692},{"x":851,"y":1692}]},"text":","},{"property":{"detectedLanguages":[{"languageCode":"zh-Hant","confidence":0}],"detectedBreak":null},"boundingBox":{"vertices":[{"x":863,"y":1640},{"x":890,"y":1640},{"x":890,"y":1684},{"x":863,"y":1684}]},"text":"2"},{"property":{"detectedLanguages":[{"languageCode":"zh-Hant","confidence":0}],"detectedBreak":null},"boundingBox":{"vertices":[{"x":892,"y":1640},{"x":921,"y":1640},{"x":921,"y":1684},{"x":892,"y":1684}]},"text":"2"},{"property":{"detectedLanguages":[{"languageCode":"zh-Hant","confidence":0}],"detectedBreak":null},"boundingBox":{"vertices":[{"x":923,"y":1640},{"x":948,"y":1640},{"x":948,"y":1684},{"x":923,"y":1684}]},"text":"8"}]},{"property":{"detectedLanguages":[{"languageCode":"zh-Hans","confidence":0}],"detectedBreak":null},"boundingBox":{"vertices":[{"x":970,"y":1638},{"x":1203,"y":1638},{"x":1203,"y":1691},{"x":970,"y":1691}]},"symbols":[{"property":{"detectedLanguages":[{"languageCode":"zh-Hant","confidence":0}],"detectedBreak":null},"boundingBox":{"vertices":[{"x":970,"y":1638},{"x":1021,"y":1638},{"x":1021,"y":1691},{"x":970,"y":1691}]},"text":"平"},{"property":{"detectedLanguages":[{"languageCode":"zh-Hant","confidence":0}],"detectedBreak":null},"boundingBox":{"vertices":[{"x":1031,"y":1641},{"x":1082,"y":1641},{"x":1082,"y":1687},{"x":1031,"y":1687}]},"text":"方"},{"property":{"detectedLanguages":[{"languageCode":"zh-Hant","confidence":0}],"detectedBreak":null},"boundingBox":{"vertices":[{"x":1091,"y":1640},{"x":1140,"y":1640},{"x":1140,"y":1687},{"x":1091,"y":1687}]},"text":"公"},{"property":{"detectedLanguages":[{"languageCode":"zh-Hant","confidence":0}],"detectedBreak":null},"boundingBox":{"vertices":[{"x":1148,"y":1643},{"x":1202,"y":1643},{"x":1202,"y":1687},{"x":1148,"y":1687}]},"text":"尺"}]},{"property":{"detectedLanguages":[{"languageCode":"en","confidence":0}],"detectedBreak":null},"boundingBox":{"vertices":[{"x":1225,"y":1657},{"x":1240,"y":1657},{"x":1240,"y":1672},{"x":1225,"y":1672}]},"symbols":[{"property":{"detectedLanguages":[{"languageCode":"zh-Hant","confidence":0}],"detectedBreak":{"type":"EOL_SURE_SPACE","isPrefix":false}},"boundingBox":{"vertices":[{"x":1225,"y":1657},{"x":1240,"y":1657},{"x":1240,"y":1672},{"x":1225,"y":1672}]},"text":"。"}]}]}],"blockType":"TEXT"},{"property":{"detectedLanguages":[{"languageCode":"zh-Hant","confidence":0}],"detectedBreak":null},"boundingBox":{"vertices":[{"x":416,"y":1789},{"x":2114,"y":1789},{"x":2114,"y":1842},{"x":416,"y":1842}]},"paragraphs":[{"property":{"detectedLanguages":[{"languageCode":"zh-Hant","confidence":0}],"detectedBreak":null},"boundingBox":{"vertices":[{"x":416,"y":1789},{"x":2114,"y":1789},{"x":2114,"y":1842},{"x":416,"y":1842}]},"words":[{"property":{"detectedLanguages":[{"languageCode":"zh-Hans","confidence":0}],"detectedBreak":null},"boundingBox":{"vertices":[{"x":416,"y":1801},{"x":462,"y":1801},{"x":462,"y":1833},{"x":416,"y":1833}]},"symbols":[{"property":{"detectedLanguages":[{"languageCode":"zh-Hant","confidence":0}],"detectedBreak":null},"boundingBox":{"vertices":[{"x":416,"y":1801},{"x":462,"y":1801},{"x":462,"y":1833},{"x":416,"y":1833}]},"text":"四"}]},{"property":{"detectedLanguages":[{"languageCode":"en","confidence":0}],"detectedBreak":null},"boundingBox":{"vertices":[{"x":486,"y":1806},{"x":503,"y":1806},{"x":503,"y":1821},{"x":486,"y":1821}]},"symbols":[{"property":{"detectedLanguages":[{"languageCode":"zh-Hant","confidence":0}],"detectedBreak":null},"boundingBox":{"vertices":[{"x":486,"y":1806},{"x":503,"y":1806},{"x":503,"y":1821},{"x":486,"y":1821}]},"text":"、"}]},{"property":{"detectedLanguages":[{"languageCode":"zh-Hans","confidence":0}],"detectedBreak":null},"boundingBox":{"vertices":[{"x":524,"y":1790},{"x":631,"y":1790},{"x":631,"y":1839},{"x":524,"y":1839}]},"symbols":[{"property":{"detectedLanguages":[{"languageCode":"zh-Hant","confidence":0}],"detectedBreak":null},"boundingBox":{"vertices":[{"x":524,"y":1792},{"x":577,"y":1792},{"x":577,"y":1836},{"x":524,"y":1836}]},"text":"法"},{"property":{"detectedLanguages":[{"languageCode":"zh-Hant","confidence":0}],"detectedBreak":null},"boundingBox":{"vertices":[{"x":582,"y":1790},{"x":631,"y":1790},{"x":631,"y":1839},{"x":582,"y":1839}]},"text":"令"}]},{"property":{"detectedLanguages":[{"languageCode":"zh-Hant","confidence":0}],"detectedBreak":null},"boundingBox":{"vertices":[{"x":640,"y":1789},{"x":753,"y":1789},{"x":753,"y":1840},{"x":640,"y":1840}]},"symbols":[{"property":{"detectedLanguages":[{"languageCode":"zh-Hant","confidence":0}],"detectedBreak":null},"boundingBox":{"vertices":[{"x":640,"y":1794},{"x":693,"y":1794},{"x":693,"y":1836},{"x":640,"y":1836}]},"text":"依"},{"property":{"detectedLanguages":[{"languageCode":"zh-Hant","confidence":0}],"detectedBreak":null},"boundingBox":{"vertices":[{"x":697,"y":1789},{"x":753,"y":1789},{"x":753,"y":1840},{"x":697,"y":1840}]},"text":"據"}]},{"property":{"detectedLanguages":[{"languageCode":"en","confidence":0}],"detectedBreak":null},"boundingBox":{"vertices":[{"x":774,"y":1796},{"x":785,"y":1796},{"x":785,"y":1828},{"x":774,"y":1828}]},"symbols":[{"property":{"detectedLanguages":[{"languageCode":"zh-Hant","confidence":0}],"detectedBreak":null},"boundingBox":{"vertices":[{"x":774,"y":1796},{"x":785,"y":1796},{"x":785,"y":1828},{"x":774,"y":1828}]},"text":":"}]},{"property":{"detectedLanguages":[{"languageCode":"zh-Hans","confidence":0}],"detectedBreak":null},"boundingBox":{"vertices":[{"x":808,"y":1792},{"x":919,"y":1792},{"x":919,"y":1841},{"x":808,"y":1841}]},"symbols":[{"property":{"detectedLanguages":[{"languageCode":"zh-Hant","confidence":0}],"detectedBreak":null},"boundingBox":{"vertices":[{"x":808,"y":1792},{"x":862,"y":1792},{"x":862,"y":1838},{"x":808,"y":1838}]},"text":"都"},{"property":{"detectedLanguages":[{"languageCode":"zh-Hant","confidence":0}],"detectedBreak":null},"boundingBox":{"vertices":[{"x":870,"y":1792},{"x":919,"y":1792},{"x":919,"y":1841},{"x":870,"y":1841}]},"text":"市"}]},{"property":{"detectedLanguages":[{"languageCode":"zh-Hans","confidence":0}],"detectedBreak":null},"boundingBox":{"vertices":[{"x":928,"y":1790},{"x":1035,"y":1790},{"x":1035,"y":1841},{"x":928,"y":1841}]},"symbols":[{"property":{"detectedLanguages":[{"languageCode":"zh-Hant","confidence":0}],"detectedBreak":null},"boundingBox":{"vertices":[{"x":928,"y":1790},{"x":977,"y":1790},{"x":977,"y":1841},{"x":928,"y":1841}]},"text":"更"},{"property":{"detectedLanguages":[{"languageCode":"zh-Hant","confidence":0}],"detectedBreak":null},"boundingBox":{"vertices":[{"x":987,"y":1790},{"x":1036,"y":1790},{"x":1036,"y":1836},{"x":987,"y":1836}]},"text":"新"}]},{"property":{"detectedLanguages":[{"languageCode":"zh-Hant","confidence":0}],"detectedBreak":null},"boundingBox":{"vertices":[{"x":1045,"y":1792},{"x":1154,"y":1792},{"x":1154,"y":1841},{"x":1045,"y":1841}]},"symbols":[{"property":{"detectedLanguages":[{"languageCode":"zh-Hant","confidence":0}],"detectedBreak":null},"boundingBox":{"vertices":[{"x":1045,"y":1792},{"x":1098,"y":1792},{"x":1098,"y":1839},{"x":1045,"y":1839}]},"text":"條"},{"property":{"detectedLanguages":[{"languageCode":"zh-Hant","confidence":0}],"detectedBreak":null},"boundingBox":{"vertices":[{"x":1103,"y":1792},{"x":1154,"y":1792},{"x":1154,"y":1841},{"x":1103,"y":1841}]},"text":"例"}]},{"property":{"detectedLanguages":[{"languageCode":"ja","confidence":0}],"detectedBreak":null},"boundingBox":{"vertices":[{"x":1168,"y":1789},{"x":1210,"y":1789},{"x":1210,"y":1840},{"x":1168,"y":1840}]},"symbols":[{"property":{"detectedLanguages":[{"languageCode":"zh-Hant","confidence":0}],"detectedBreak":null},"boundingBox":{"vertices":[{"x":1168,"y":1789},{"x":1210,"y":1789},{"x":1210,"y":1840},{"x":1168,"y":1840}]},"text":"第"}]},{"property":{"detectedLanguages":[{"languageCode":"en","confidence":0}],"detectedBreak":null},"boundingBox":{"vertices":[{"x":1240,"y":1792},{"x":1282,"y":1792},{"x":1282,"y":1836},{"x":1240,"y":1836}]},"symbols":[{"property":{"detectedLanguages":[{"languageCode":"zh-Hant","confidence":0}],"detectedBreak":null},"boundingBox":{"vertices":[{"x":1240,"y":1792},{"x":1258,"y":1792},{"x":1258,"y":1836},{"x":1240,"y":1836}]},"text":"1"},{"property":{"detectedLanguages":[{"languageCode":"zh-Hant","confidence":0}],"detectedBreak":null},"boundingBox":{"vertices":[{"x":1261,"y":1792},{"x":1283,"y":1792},{"x":1283,"y":1836},{"x":1261,"y":1836}]},"text":"1"}]},{"property":{"detectedLanguages":[{"languageCode":"zh-Hant","confidence":0}],"detectedBreak":null},"boundingBox":{"vertices":[{"x":1305,"y":1792},{"x":1359,"y":1792},{"x":1359,"y":1838},{"x":1305,"y":1838}]},"symbols":[{"property":{"detectedLanguages":[{"languageCode":"zh-Hant","confidence":0}],"detectedBreak":null},"boundingBox":{"vertices":[{"x":1305,"y":1792},{"x":1359,"y":1792},{"x":1359,"y":1838},{"x":1305,"y":1838}]},"text":"條"}]},{"property":{"detectedLanguages":[{"languageCode":"zh-Hans","confidence":0}],"detectedBreak":null},"boundingBox":{"vertices":[{"x":1365,"y":1792},{"x":1418,"y":1792},{"x":1418,"y":1836},{"x":1365,"y":1836}]},"symbols":[{"property":{"detectedLanguages":[{"languageCode":"zh-Hant","confidence":0}],"detectedBreak":null},"boundingBox":{"vertices":[{"x":1365,"y":1792},{"x":1418,"y":1792},{"x":1418,"y":1836},{"x":1365,"y":1836}]},"text":"及"}]},{"property":{"detectedLanguages":[{"languageCode":"zh-Hant","confidence":0}],"detectedBreak":null},"boundingBox":{"vertices":[{"x":1429,"y":1789},{"x":1593,"y":1789},{"x":1593,"y":1842},{"x":1429,"y":1842}]},"symbols":[{"property":{"detectedLanguages":[{"languageCode":"zh-Hant","confidence":0}],"detectedBreak":null},"boundingBox":{"vertices":[{"x":1429,"y":1789},{"x":1475,"y":1789},{"x":1475,"y":1842},{"x":1429,"y":1842}]},"text":"臺"},{"property":{"detectedLanguages":[{"languageCode":"zh-Hant","confidence":0}],"detectedBreak":null},"boundingBox":{"vertices":[{"x":1484,"y":1792},{"x":1537,"y":1792},{"x":1537,"y":1838},{"x":1484,"y":1838}]},"text":"北"},{"property":{"detectedLanguages":[{"languageCode":"zh-Hant","confidence":0}],"detectedBreak":null},"boundingBox":{"vertices":[{"x":1542,"y":1792},{"x":1593,"y":1792},{"x":1593,"y":1841},{"x":1542,"y":1841}]},"text":"市"}]},{"property":{"detectedLanguages":[{"languageCode":"zh-Hans","confidence":0}],"detectedBreak":null},"boundingBox":{"vertices":[{"x":1599,"y":1792},{"x":1708,"y":1792},{"x":1708,"y":1841},{"x":1599,"y":1841}]},"symbols":[{"property":{"detectedLanguages":[{"languageCode":"zh-Hant","confidence":0}],"detectedBreak":null},"boundingBox":{"vertices":[{"x":1599,"y":1792},{"x":1650,"y":1792},{"x":1650,"y":1836},{"x":1599,"y":1836}]},"text":"都"},{"property":{"detectedLanguages":[{"languageCode":"zh-Hant","confidence":0}],"detectedBreak":null},"boundingBox":{"vertices":[{"x":1659,"y":1792},{"x":1708,"y":1792},{"x":1708,"y":1841},{"x":1659,"y":1841}]},"text":"市"}]},{"property":{"detectedLanguages":[{"languageCode":"zh-Hans","confidence":0}],"detectedBreak":null},"boundingBox":{"vertices":[{"x":1720,"y":1790},{"x":1826,"y":1790},{"x":1826,"y":1841},{"x":1720,"y":1841}]},"symbols":[{"property":{"detectedLanguages":[{"languageCode":"zh-Hant","confidence":0}],"detectedBreak":null},"boundingBox":{"vertices":[{"x":1720,"y":1790},{"x":1769,"y":1790},{"x":1769,"y":1841},{"x":1720,"y":1841}]},"text":"更"},{"property":{"detectedLanguages":[{"languageCode":"zh-Hant","confidence":0}],"detectedBreak":null},"boundingBox":{"vertices":[{"x":1775,"y":1790},{"x":1826,"y":1790},{"x":1826,"y":1837},{"x":1775,"y":1837}]},"text":"新"}]},{"property":{"detectedLanguages":[{"languageCode":"zh-Hans","confidence":0}],"detectedBreak":null},"boundingBox":{"vertices":[{"x":1842,"y":1790},{"x":1943,"y":1790},{"x":1943,"y":1837},{"x":1842,"y":1837}]},"symbols":[{"property":{"detectedLanguages":[{"languageCode":"zh-Hant","confidence":0}],"detectedBreak":null},"boundingBox":{"vertices":[{"x":1842,"y":1790},{"x":1872,"y":1790},{"x":1872,"y":1837},{"x":1842,"y":1837}]},"text":"自"},{"property":{"detectedLanguages":[{"languageCode":"zh-Hant","confidence":0}],"detectedBreak":null},"boundingBox":{"vertices":[{"x":1892,"y":1792},{"x":1943,"y":1792},{"x":1943,"y":1836},{"x":1892,"y":1836}]},"text":"治"}]},{"property":{"detectedLanguages":[{"languageCode":"zh-Hant","confidence":0}],"detectedBreak":null},"boundingBox":{"vertices":[{"x":1952,"y":1792},{"x":2059,"y":1792},{"x":2059,"y":1839},{"x":1952,"y":1839}]},"symbols":[{"property":{"detectedLanguages":[{"languageCode":"zh-Hant","confidence":0}],"detectedBreak":null},"boundingBox":{"vertices":[{"x":1952,"y":1792},{"x":2003,"y":1792},{"x":2003,"y":1839},{"x":1952,"y":1839}]},"text":"條"},{"property":{"detectedLanguages":[{"languageCode":"zh-Hant","confidence":0}],"detectedBreak":null},"boundingBox":{"vertices":[{"x":2010,"y":1792},{"x":2059,"y":1792},{"x":2059,"y":1839},{"x":2010,"y":1839}]},"text":"例"}]},{"property":{"detectedLanguages":[{"languageCode":"ja","confidence":0}],"detectedBreak":null},"boundingBox":{"vertices":[{"x":2072,"y":1789},{"x":2114,"y":1789},{"x":2114,"y":1840},{"x":2072,"y":1840}]},"symbols":[{"property":{"detectedLanguages":[{"languageCode":"zh-Hant","confidence":0}],"detectedBreak":{"type":"EOL_SURE_SPACE","isPrefix":false}},"boundingBox":{"vertices":[{"x":2072,"y":1789},{"x":2114,"y":1789},{"x":2114,"y":1840},{"x":2072,"y":1840}]},"text":"第"}]}]}],"blockType":"TEXT"},{"property":{"detectedLanguages":[{"languageCode":"zh-Hant","confidence":0}],"detectedBreak":null},"boundingBox":{"vertices":[{"x":807,"y":1940},{"x":967,"y":1940},{"x":967,"y":1988},{"x":807,"y":1988}]},"paragraphs":[{"property":{"detectedLanguages":[{"languageCode":"zh-Hant","confidence":0}],"detectedBreak":null},"boundingBox":{"vertices":[{"x":807,"y":1940},{"x":968,"y":1940},{"x":968,"y":1989},{"x":807,"y":1989}]},"words":[{"property":{"detectedLanguages":[{"languageCode":"en","confidence":0}],"detectedBreak":null},"boundingBox":{"vertices":[{"x":807,"y":1940},{"x":857,"y":1940},{"x":857,"y":1985},{"x":807,"y":1985}]},"symbols":[{"property":{"detectedLanguages":[{"languageCode":"zh-Hant","confidence":0}],"detectedBreak":null},"boundingBox":{"vertices":[{"x":807,"y":1940},{"x":831,"y":1940},{"x":831,"y":1985},{"x":807,"y":1985}]},"text":"1"},{"property":{"detectedLanguages":[{"languageCode":"zh-Hant","confidence":0}],"detectedBreak":null},"boundingBox":{"vertices":[{"x":834,"y":1940},{"x":856,"y":1940},{"x":856,"y":1985},{"x":834,"y":1985}]},"text":"5"}]},{"property":{"detectedLanguages":[{"languageCode":"zh-Hant","confidence":0}],"detectedBreak":null},"boundingBox":{"vertices":[{"x":877,"y":1940},{"x":927,"y":1940},{"x":927,"y":1988},{"x":877,"y":1988}]},"symbols":[{"property":{"detectedLanguages":[{"languageCode":"zh-Hant","confidence":0}],"detectedBreak":null},"boundingBox":{"vertices":[{"x":877,"y":1940},{"x":927,"y":1940},{"x":927,"y":1988},{"x":877,"y":1988}]},"text":"條"}]},{"property":{"detectedLanguages":[{"languageCode":"en","confidence":0}],"detectedBreak":null},"boundingBox":{"vertices":[{"x":951,"y":1957},{"x":967,"y":1957},{"x":967,"y":1969},{"x":951,"y":1969}]},"symbols":[{"property":{"detectedLanguages":[{"languageCode":"zh-Hant","confidence":0}],"detectedBreak":{"type":"EOL_SURE_SPACE","isPrefix":false}},"boundingBox":{"vertices":[{"x":951,"y":1957},{"x":967,"y":1957},{"x":967,"y":1969},{"x":951,"y":1969}]},"text":"。"}]}]}],"blockType":"TEXT"},{"property":{"detectedLanguages":[{"languageCode":"zh-Hans","confidence":0}],"detectedBreak":null},"boundingBox":{"vertices":[{"x":2106,"y":2140},{"x":2135,"y":2140},{"x":2135,"y":2179},{"x":2106,"y":2179}]},"paragraphs":[{"property":{"detectedLanguages":[{"languageCode":"zh-Hans","confidence":0}],"detectedBreak":null},"boundingBox":{"vertices":[{"x":2106,"y":2140},{"x":2135,"y":2140},{"x":2135,"y":2179},{"x":2106,"y":2179}]},"words":[{"property":{"detectedLanguages":[{"languageCode":"zh-Hans","confidence":0}],"detectedBreak":null},"boundingBox":{"vertices":[{"x":2106,"y":2140},{"x":2135,"y":2140},{"x":2135,"y":2179},{"x":2106,"y":2179}]},"symbols":[{"property":{"detectedLanguages":[{"languageCode":"zh-Hant","confidence":0}],"detectedBreak":{"type":"EOL_SURE_SPACE","isPrefix":false}},"boundingBox":{"vertices":[{"x":2106,"y":2140},{"x":2135,"y":2140},{"x":2135,"y":2179},{"x":2106,"y":2179}]},"text":"厅"}]}]}],"blockType":"TEXT"},{"property":{"detectedLanguages":[{"languageCode":"zh-Hans","confidence":0}],"detectedBreak":null},"boundingBox":{"vertices":[{"x":1789,"y":3168},{"x":1830,"y":3170},{"x":1828,"y":3211},{"x":1787,"y":3209}]},"paragraphs":[{"property":{"detectedLanguages":[{"languageCode":"zh-Hans","confidence":0}],"detectedBreak":null},"boundingBox":{"vertices":[{"x":1787,"y":3168},{"x":1831,"y":3168},{"x":1831,"y":3212},{"x":1787,"y":3212}]},"words":[{"property":{"detectedLanguages":[{"languageCode":"zh-Hans","confidence":0}],"detectedBreak":null},"boundingBox":{"vertices":[{"x":1789,"y":3168},{"x":1830,"y":3170},{"x":1828,"y":3211},{"x":1787,"y":3209}]},"symbols":[{"property":{"detectedLanguages":[{"languageCode":"zh-Hant","confidence":0}],"detectedBreak":{"type":"EOL_SURE_SPACE","isPrefix":false}},"boundingBox":{"vertices":[{"x":1789,"y":3168},{"x":1830,"y":3170},{"x":1828,"y":3211},{"x":1787,"y":3209}]},"text":"企"}]}]}],"blockType":"TEXT"}]}],"text":"案名:劃定臺北市大安區瑞安段一小段221-3地號等3筆土地為更\n新單元檢討書\n申請人:趙玉琴\n一、計畫位置:本更新單元位於臺北市大安區建國南路二段69巷,\n信義路三段134巷及建國南路二段所圍街廓內之東\n二、計畫範圍:臺北市大安區瑞安段一小段221-3 , 225、226地號\n等3筆土地。\n三、計畫面積: 1,228平方公尺。\n四、法令依據:都市更新條例第11條及臺北市都市更新自治條例第\n15條。\n厅\n企\n"},"safeSearchAnnotation":null,"imagePropertiesAnnotation":null,"cropHintsAnnotation":null,"webDetection":null,"error":null}]}]